{
"meta":{"test_sets":[],"test_metrics":[],"learn_metrics":[{"best_value":"Min","name":"RMSE"}],"launch_mode":"Train","parameters":"","iteration_count":1000,"learn_sets":["learn"],"name":"experiment"},
"iterations":[
{"learn":[14.81573271],"iteration":0,"passed_time":0.001519678192,"remaining_time":1.518158513},
{"learn":[14.4365345],"iteration":1,"passed_time":0.003860039476,"remaining_time":1.926159699},
{"learn":[14.05231599],"iteration":2,"passed_time":0.005356325278,"remaining_time":1.780085434},
{"learn":[13.68198743],"iteration":3,"passed_time":0.006267329014,"remaining_time":1.560564924},
{"learn":[13.353467],"iteration":4,"passed_time":0.007217501225,"remaining_time":1.436282744},
{"learn":[13.05673067],"iteration":5,"passed_time":0.008195683939,"remaining_time":1.357751639},
{"learn":[12.75130162],"iteration":6,"passed_time":0.009160082039,"remaining_time":1.299423066},
{"learn":[12.46608694],"iteration":7,"passed_time":0.01013989518,"remaining_time":1.257347002},
{"learn":[12.19956623],"iteration":8,"passed_time":0.01118445455,"remaining_time":1.231532718},
{"learn":[11.90448584],"iteration":9,"passed_time":0.01252095842,"remaining_time":1.239574884},
{"learn":[11.62728386],"iteration":10,"passed_time":0.01494247958,"remaining_time":1.343464755},
{"learn":[11.37117893],"iteration":11,"passed_time":0.01672457165,"remaining_time":1.376989733},
{"learn":[11.15566896],"iteration":12,"passed_time":0.01868173988,"remaining_time":1.418375174},
{"learn":[10.95368871],"iteration":13,"passed_time":0.020384899,"remaining_time":1.435679315},
{"learn":[10.71159073],"iteration":14,"passed_time":0.02168701822,"remaining_time":1.424114196},
{"learn":[10.47283814],"iteration":15,"passed_time":0.02375717834,"remaining_time":1.461066468},
{"learn":[10.24513454],"iteration":16,"passed_time":0.02508917872,"remaining_time":1.450744863},
{"learn":[10.03626055],"iteration":17,"passed_time":0.02667098175,"remaining_time":1.455050227},
{"learn":[9.818259627],"iteration":18,"passed_time":0.03187677183,"remaining_time":1.645848061},
{"learn":[9.622988458],"iteration":19,"passed_time":0.0336435396,"remaining_time":1.64853344},
{"learn":[9.453008889],"iteration":20,"passed_time":0.03650151207,"remaining_time":1.701665729},
{"learn":[9.270240771],"iteration":21,"passed_time":0.03872186641,"remaining_time":1.721362971},
{"learn":[9.122084489],"iteration":22,"passed_time":0.04004108077,"remaining_time":1.700875475},
{"learn":[8.956200044],"iteration":23,"passed_time":0.04105483108,"remaining_time":1.66956313},
{"learn":[8.797889965],"iteration":24,"passed_time":0.04258032131,"remaining_time":1.660632531},
{"learn":[8.658873061],"iteration":25,"passed_time":0.05209901486,"remaining_time":1.951709249},
{"learn":[8.515757986],"iteration":26,"passed_time":0.05386281931,"remaining_time":1.941056414},
{"learn":[8.388237734],"iteration":27,"passed_time":0.05521378451,"remaining_time":1.916707091},
{"learn":[8.257462449],"iteration":28,"passed_time":0.0572392306,"remaining_time":1.916527342},
{"learn":[8.131342801],"iteration":29,"passed_time":0.05904991486,"remaining_time":1.909280581},
{"learn":[8.015973228],"iteration":30,"passed_time":0.06043521982,"remaining_time":1.889088},
{"learn":[7.914234004],"iteration":31,"passed_time":0.06175784403,"remaining_time":1.868174782},
{"learn":[7.792085135],"iteration":32,"passed_time":0.06368224753,"remaining_time":1.866082829},
{"learn":[7.696438925],"iteration":33,"passed_time":0.06609962576,"remaining_time":1.878007014},
{"learn":[7.584414577],"iteration":34,"passed_time":0.06733988615,"remaining_time":1.856656861},
{"learn":[7.492635228],"iteration":35,"passed_time":0.06867730313,"remaining_time":1.839025562},
{"learn":[7.398035673],"iteration":36,"passed_time":0.07178192391,"remaining_time":1.868270074},
{"learn":[7.314267161],"iteration":37,"passed_time":0.07400973457,"remaining_time":1.873614859},
{"learn":[7.221968722],"iteration":38,"passed_time":0.07547504081,"remaining_time":1.859782416},
{"learn":[7.143885728],"iteration":39,"passed_time":0.07661577871,"remaining_time":1.838778689},
{"learn":[7.061477761],"iteration":40,"passed_time":0.07794463094,"remaining_time":1.823143929},
{"learn":[6.980158677],"iteration":41,"passed_time":0.07961143925,"remaining_time":1.815899019},
{"learn":[6.901859261],"iteration":42,"passed_time":0.08080917718,"remaining_time":1.798474013},
{"learn":[6.834766196],"iteration":43,"passed_time":0.08379949751,"remaining_time":1.820734537},
{"learn":[6.76532915],"iteration":44,"passed_time":0.08571640935,"remaining_time":1.819092687},
{"learn":[6.697660367],"iteration":45,"passed_time":0.08710733962,"remaining_time":1.806530478},
{"learn":[6.628873774],"iteration":46,"passed_time":0.0896764379,"remaining_time":1.818332879},
{"learn":[6.574418402],"iteration":47,"passed_time":0.09122469873,"remaining_time":1.809289858},
{"learn":[6.513952778],"iteration":48,"passed_time":0.09311716991,"remaining_time":1.807233236},
{"learn":[6.459335858],"iteration":49,"passed_time":0.09435311305,"remaining_time":1.792709148},
{"learn":[6.409338838],"iteration":50,"passed_time":0.09596586031,"remaining_time":1.785717675},
{"learn":[6.359407778],"iteration":51,"passed_time":0.09805999499,"remaining_time":1.787709139},
{"learn":[6.317740788],"iteration":52,"passed_time":0.09945020937,"remaining_time":1.776968835},
{"learn":[6.272013091],"iteration":53,"passed_time":0.1012152674,"remaining_time":1.773141537},
{"learn":[6.229837678],"iteration":54,"passed_time":0.1026643668,"remaining_time":1.763960484},
{"learn":[6.190197379],"iteration":55,"passed_time":0.1036953073,"remaining_time":1.748006609},
{"learn":[6.152271715],"iteration":56,"passed_time":0.1046578391,"remaining_time":1.7314446},
{"learn":[6.119278867],"iteration":57,"passed_time":0.1058026898,"remaining_time":1.718381617},
{"learn":[6.079885281],"iteration":58,"passed_time":0.1074958548,"remaining_time":1.714467786},
{"learn":[6.049443205],"iteration":59,"passed_time":0.1090273018,"remaining_time":1.708094394},
{"learn":[6.018726647],"iteration":60,"passed_time":0.115545922,"remaining_time":1.778649521},
{"learn":[5.979571256],"iteration":61,"passed_time":0.1165983341,"remaining_time":1.764019958},
{"learn":[5.949689772],"iteration":62,"passed_time":0.1175960084,"remaining_time":1.7490073},
{"learn":[5.917237324],"iteration":63,"passed_time":0.1186591271,"remaining_time":1.735389734},
{"learn":[5.887759522],"iteration":64,"passed_time":0.1197536314,"remaining_time":1.722609928},
{"learn":[5.85591482],"iteration":65,"passed_time":0.1206645449,"remaining_time":1.707586135},
{"learn":[5.827913663],"iteration":66,"passed_time":0.1214855484,"remaining_time":1.691731592},
{"learn":[5.800866663],"iteration":67,"passed_time":0.122342014,"remaining_time":1.676805251},
{"learn":[5.775580749],"iteration":68,"passed_time":0.1233849191,"remaining_time":1.664802314},
{"learn":[5.750700947],"iteration":69,"passed_time":0.1246684851,"remaining_time":1.656309874},
{"learn":[5.726778143],"iteration":70,"passed_time":0.1264847407,"remaining_time":1.654990481},
{"learn":[5.705969782],"iteration":71,"passed_time":0.1282681867,"remaining_time":1.653234407},
{"learn":[5.685870776],"iteration":72,"passed_time":0.1293429591,"remaining_time":1.642478399},
{"learn":[5.661533885],"iteration":73,"passed_time":0.1304580477,"remaining_time":1.632488542},
{"learn":[5.642362048],"iteration":74,"passed_time":0.1313391855,"remaining_time":1.619849955},
{"learn":[5.622303129],"iteration":75,"passed_time":0.1321964735,"remaining_time":1.607230809},
{"learn":[5.605084201],"iteration":76,"passed_time":0.1331038768,"remaining_time":1.5955179},
{"learn":[5.588359684],"iteration":77,"passed_time":0.1340352294,"remaining_time":1.584365147},
{"learn":[5.571436045],"iteration":78,"passed_time":0.135197139,"remaining_time":1.576159051},
{"learn":[5.548660852],"iteration":79,"passed_time":0.1362949829,"remaining_time":1.567392303},
{"learn":[5.531873061],"iteration":80,"passed_time":0.1375993639,"remaining_time":1.561158215},
{"learn":[5.515915066],"iteration":81,"passed_time":0.1393759343,"remaining_time":1.560330581},
{"learn":[5.496581763],"iteration":82,"passed_time":0.1409641659,"remaining_time":1.557399279},
{"learn":[5.482333156],"iteration":83,"passed_time":0.142310128,"remaining_time":1.551858063},
{"learn":[5.469477335],"iteration":84,"passed_time":0.1434028963,"remaining_time":1.543690002},
{"learn":[5.450473452],"iteration":85,"passed_time":0.14476354,"remaining_time":1.538533436},
{"learn":[5.43611642],"iteration":86,"passed_time":0.1457833893,"remaining_time":1.529887752},
{"learn":[5.425468658],"iteration":87,"passed_time":0.1467962375,"remaining_time":1.521342825},
{"learn":[5.414704284],"iteration":88,"passed_time":0.1478457417,"remaining_time":1.513342367},
{"learn":[5.401754058],"iteration":89,"passed_time":0.148707854,"remaining_time":1.503601635},
{"learn":[5.38764774],"iteration":90,"passed_time":0.1496119769,"remaining_time":1.494475682},
{"learn":[5.376484062],"iteration":91,"passed_time":0.150661802,"remaining_time":1.486966481},
{"learn":[5.361500586],"iteration":92,"passed_time":0.1526383864,"remaining_time":1.488634585},
{"learn":[5.351714688],"iteration":93,"passed_time":0.1544838918,"remaining_time":1.488961765},
{"learn":[5.343613993],"iteration":94,"passed_time":0.1558857837,"remaining_time":1.485017203},
{"learn":[5.333400841],"iteration":95,"passed_time":0.1570302835,"remaining_time":1.478701836},
{"learn":[5.324684122],"iteration":96,"passed_time":0.158088242,"remaining_time":1.471687449},
{"learn":[5.315602677],"iteration":97,"passed_time":0.1592165139,"remaining_time":1.465441791},
{"learn":[5.30765282],"iteration":98,"passed_time":0.1602865383,"remaining_time":1.458769404},
{"learn":[5.298304869],"iteration":99,"passed_time":0.1613974691,"remaining_time":1.452577222},
{"learn":[5.288471971],"iteration":100,"passed_time":0.1624432434,"remaining_time":1.445905701},
{"learn":[5.279255526],"iteration":101,"passed_time":0.1634409077,"remaining_time":1.438920932},
{"learn":[5.270596765],"iteration":102,"passed_time":0.1646424055,"remaining_time":1.433827551},
{"learn":[5.258017631],"iteration":103,"passed_time":0.1662133271,"remaining_time":1.431991741},
{"learn":[5.246919356],"iteration":104,"passed_time":0.1688949846,"remaining_time":1.439628678},
{"learn":[5.241737401],"iteration":105,"passed_time":0.1706152489,"remaining_time":1.438962571},
{"learn":[5.2356658],"iteration":106,"passed_time":0.1715828061,"remaining_time":1.431994821},
{"learn":[5.228609655],"iteration":107,"passed_time":0.1725301038,"remaining_time":1.424970858},
{"learn":[5.221611246],"iteration":108,"passed_time":0.1740716104,"remaining_time":1.422915641},
{"learn":[5.214248349],"iteration":109,"passed_time":0.1750354077,"remaining_time":1.416195571},
{"learn":[5.203710054],"iteration":110,"passed_time":0.1760699386,"remaining_time":1.410145724},
{"learn":[5.197972573],"iteration":111,"passed_time":0.1769560704,"remaining_time":1.403008844},
{"learn":[5.190610758],"iteration":112,"passed_time":0.1779444469,"remaining_time":1.396785171},
{"learn":[5.182205063],"iteration":113,"passed_time":0.1794053313,"remaining_time":1.394325645},
{"learn":[5.175267177],"iteration":114,"passed_time":0.1806902049,"remaining_time":1.390528968},
{"learn":[5.167513061],"iteration":115,"passed_time":0.1822989458,"remaining_time":1.389243691},
{"learn":[5.162529378],"iteration":116,"passed_time":0.1836727676,"remaining_time":1.386179947},
{"learn":[5.157087492],"iteration":117,"passed_time":0.1850384401,"remaining_time":1.383083933},
{"learn":[5.152042446],"iteration":118,"passed_time":0.18606048,"remaining_time":1.377472966},
{"learn":[5.146845571],"iteration":119,"passed_time":0.1870265076,"remaining_time":1.371527723},
{"learn":[5.139609267],"iteration":120,"passed_time":0.188057589,"remaining_time":1.366137361},
{"learn":[5.135993075],"iteration":121,"passed_time":0.1890707275,"remaining_time":1.360689334},
{"learn":[5.130236842],"iteration":122,"passed_time":0.1901199208,"remaining_time":1.355570492},
{"learn":[5.120353075],"iteration":123,"passed_time":0.1911265863,"remaining_time":1.350216852},
{"learn":[5.112212238],"iteration":124,"passed_time":0.1920804587,"remaining_time":1.344563211},
{"learn":[5.106960178],"iteration":125,"passed_time":0.193001512,"remaining_time":1.33875652},
{"learn":[5.103713363],"iteration":126,"passed_time":0.1944109266,"remaining_time":1.336383771},
{"learn":[5.097351478],"iteration":127,"passed_time":0.1964926445,"remaining_time":1.33860614},
{"learn":[5.092974609],"iteration":128,"passed_time":0.1982317824,"remaining_time":1.338448701},
{"learn":[5.089822173],"iteration":129,"passed_time":0.1993036469,"remaining_time":1.333801329},
{"learn":[5.082511827],"iteration":130,"passed_time":0.2003499761,"remaining_time":1.329039155},
{"learn":[5.075651217],"iteration":131,"passed_time":0.201637719,"remaining_time":1.325920758},
{"learn":[5.065502961],"iteration":132,"passed_time":0.2031711021,"remaining_time":1.324431169},
{"learn":[5.06051156],"iteration":133,"passed_time":0.2045301511,"remaining_time":1.32181426},
{"learn":[5.0557301],"iteration":134,"passed_time":0.2056553001,"remaining_time":1.317717293},
{"learn":[5.049157424],"iteration":135,"passed_time":0.2073437854,"remaining_time":1.317242872},
{"learn":[5.043379474],"iteration":136,"passed_time":0.2091410418,"remaining_time":1.317435906},
{"learn":[5.039538745],"iteration":137,"passed_time":0.2121000358,"remaining_time":1.324856746},
{"learn":[5.034469474],"iteration":138,"passed_time":0.2132849978,"remaining_time":1.321139447},
{"learn":[5.030885806],"iteration":139,"passed_time":0.214265406,"remaining_time":1.31620178},
{"learn":[5.025759492],"iteration":140,"passed_time":0.2154371239,"remaining_time":1.312485741},
{"learn":[5.021198288],"iteration":141,"passed_time":0.2164034777,"remaining_time":1.307564675},
{"learn":[5.016558638],"iteration":142,"passed_time":0.2174620877,"remaining_time":1.303251812},
{"learn":[5.009665306],"iteration":143,"passed_time":0.2185430528,"remaining_time":1.299117036},
{"learn":[5.005464112],"iteration":144,"passed_time":0.2196038601,"remaining_time":1.29490552},
{"learn":[5.00154891],"iteration":145,"passed_time":0.224588049,"remaining_time":1.313686259},
{"learn":[4.997691384],"iteration":146,"passed_time":0.2264835943,"remaining_time":1.314221129},
{"learn":[4.995097806],"iteration":147,"passed_time":0.2283065794,"remaining_time":1.314305444},
{"learn":[4.988619624],"iteration":148,"passed_time":0.2298952179,"remaining_time":1.313025708},
{"learn":[4.982497529],"iteration":149,"passed_time":0.2310894949,"remaining_time":1.309507138},
{"learn":[4.976499381],"iteration":150,"passed_time":0.2319859465,"remaining_time":1.304344825},
{"learn":[4.974149762],"iteration":151,"passed_time":0.2335033033,"remaining_time":1.302702639},
{"learn":[4.968463456],"iteration":152,"passed_time":0.235359405,"remaining_time":1.30293736},
{"learn":[4.964858844],"iteration":153,"passed_time":0.2368231816,"remaining_time":1.300989686},
{"learn":[4.957813371],"iteration":154,"passed_time":0.2382862112,"remaining_time":1.299044184},
{"learn":[4.951427899],"iteration":155,"passed_time":0.2394643368,"remaining_time":1.295563463},
{"learn":[4.944144812],"iteration":156,"passed_time":0.2406100896,"remaining_time":1.291938252},
{"learn":[4.939454462],"iteration":157,"passed_time":0.2419222293,"remaining_time":1.289231121},
{"learn":[4.929638945],"iteration":158,"passed_time":0.2429096434,"remaining_time":1.284823963},
{"learn":[4.926231632],"iteration":159,"passed_time":0.2437715457,"remaining_time":1.279800615},
{"learn":[4.922151393],"iteration":160,"passed_time":0.2445582539,"remaining_time":1.274437112},
{"learn":[4.916240983],"iteration":161,"passed_time":0.2454213993,"remaining_time":1.26952551},
{"learn":[4.909899744],"iteration":162,"passed_time":0.2464145963,"remaining_time":1.265331393},
{"learn":[4.904086181],"iteration":163,"passed_time":0.2475100939,"remaining_time":1.261697796},
{"learn":[4.902279414],"iteration":164,"passed_time":0.2491925226,"remaining_time":1.26106519},
{"learn":[4.897662879],"iteration":165,"passed_time":0.250183318,"remaining_time":1.256945104},
{"learn":[4.893914231],"iteration":166,"passed_time":0.2513875896,"remaining_time":1.253927318},
{"learn":[4.890753758],"iteration":167,"passed_time":0.2530953367,"remaining_time":1.253424525},
{"learn":[4.885207612],"iteration":168,"passed_time":0.2542873032,"remaining_time":1.250371296},
{"learn":[4.882712147],"iteration":169,"passed_time":0.2561497175,"remaining_time":1.250613327},
{"learn":[4.878549954],"iteration":170,"passed_time":0.2570749061,"remaining_time":1.246287118},
{"learn":[4.875726323],"iteration":171,"passed_time":0.2581698415,"remaining_time":1.242817609},
{"learn":[4.872115256],"iteration":172,"passed_time":0.259119573,"remaining_time":1.238681427},
{"learn":[4.864923988],"iteration":173,"passed_time":0.260013397,"remaining_time":1.234316471},
{"learn":[4.855886576],"iteration":174,"passed_time":0.2610091801,"remaining_time":1.230471849},
{"learn":[4.854220659],"iteration":175,"passed_time":0.2622062609,"remaining_time":1.22760204},
{"learn":[4.851179015],"iteration":176,"passed_time":0.2633106437,"remaining_time":1.224320112},
{"learn":[4.84697531],"iteration":177,"passed_time":0.2650214898,"remaining_time":1.223863285},
{"learn":[4.844867667],"iteration":178,"passed_time":0.2663087614,"remaining_time":1.221449682},
{"learn":[4.840321959],"iteration":179,"passed_time":0.2672284803,"remaining_time":1.217374188},
{"learn":[4.833039109],"iteration":180,"passed_time":0.2685885022,"remaining_time":1.215325874},
{"learn":[4.83103822],"iteration":181,"passed_time":0.2695392269,"remaining_time":1.211445536},
{"learn":[4.825363552],"iteration":182,"passed_time":0.2705082522,"remaining_time":1.207678918},
{"learn":[4.819867694],"iteration":183,"passed_time":0.271445167,"remaining_time":1.203800306},
{"learn":[4.817951475],"iteration":184,"passed_time":0.2723800235,"remaining_time":1.199944428},
{"learn":[4.815234037],"iteration":185,"passed_time":0.2731451155,"remaining_time":1.195377011},
{"learn":[4.808765656],"iteration":186,"passed_time":0.2740711589,"remaining_time":1.191550012},
{"learn":[4.801803127],"iteration":187,"passed_time":0.2751573128,"remaining_time":1.188445415},
{"learn":[4.797330663],"iteration":188,"passed_time":0.2760768211,"remaining_time":1.1846471},
{"learn":[4.794150368],"iteration":189,"passed_time":0.2880307359,"remaining_time":1.227920506},
{"learn":[4.790359089],"iteration":190,"passed_time":0.2889456008,"remaining_time":1.223858592},
{"learn":[4.787385378],"iteration":191,"passed_time":0.289818875,"remaining_time":1.219654432},
{"learn":[4.785246776],"iteration":192,"passed_time":0.2908137316,"remaining_time":1.215993168},
{"learn":[4.781774486],"iteration":193,"passed_time":0.2916250667,"remaining_time":1.211596927},
{"learn":[4.77731457],"iteration":194,"passed_time":0.2925173869,"remaining_time":1.207571777},
{"learn":[4.774432717],"iteration":195,"passed_time":0.2935176186,"remaining_time":1.204021252},
{"learn":[4.771160841],"iteration":196,"passed_time":0.2945742133,"remaining_time":1.200726362},
{"learn":[4.767583002],"iteration":197,"passed_time":0.2956119281,"remaining_time":1.197377608},
{"learn":[4.764095603],"iteration":198,"passed_time":0.2966585486,"remaining_time":1.194087927},
{"learn":[4.760497189],"iteration":199,"passed_time":0.2981087412,"remaining_time":1.192434965},
{"learn":[4.757232946],"iteration":200,"passed_time":0.2990570428,"remaining_time":1.188788941},
{"learn":[4.753404291],"iteration":201,"passed_time":0.2999057865,"remaining_time":1.184776325},
{"learn":[4.745762914],"iteration":202,"passed_time":0.3009410695,"remaining_time":1.181527253},
{"learn":[4.740454659],"iteration":203,"passed_time":0.3018596452,"remaining_time":1.177844498},
{"learn":[4.736279423],"iteration":204,"passed_time":0.3028655332,"remaining_time":1.174527312},
{"learn":[4.734665777],"iteration":205,"passed_time":0.3038626359,"remaining_time":1.171198703},
{"learn":[4.731215949],"iteration":206,"passed_time":0.3048294409,"remaining_time":1.167776554},
{"learn":[4.725976531],"iteration":207,"passed_time":0.3058721807,"remaining_time":1.16466715},
{"learn":[4.723157867],"iteration":208,"passed_time":0.3068539242,"remaining_time":1.16134667},
{"learn":[4.718211152],"iteration":209,"passed_time":0.3080109086,"remaining_time":1.158707704},
{"learn":[4.716259101],"iteration":210,"passed_time":0.3092547747,"remaining_time":1.156407665},
{"learn":[4.714638292],"iteration":211,"passed_time":0.3107314094,"remaining_time":1.154982786},
{"learn":[4.711989707],"iteration":212,"passed_time":0.311807561,"remaining_time":1.152077702},
{"learn":[4.709781181],"iteration":213,"passed_time":0.31304075,"remaining_time":1.149766493},
{"learn":[4.706950467],"iteration":214,"passed_time":0.3139581422,"remaining_time":1.146312287},
{"learn":[4.702968432],"iteration":215,"passed_time":0.3148690013,"remaining_time":1.142857856},
{"learn":[4.698006191],"iteration":216,"passed_time":0.315864239,"remaining_time":1.139731332},
{"learn":[4.692855554],"iteration":217,"passed_time":0.3170138124,"remaining_time":1.137177988},
{"learn":[4.690394235],"iteration":218,"passed_time":0.31808046,"remaining_time":1.134341732},
{"learn":[4.687835047],"iteration":219,"passed_time":0.3190477512,"remaining_time":1.1311693},
{"learn":[4.681427969],"iteration":220,"passed_time":0.3199838785,"remaining_time":1.127906974},
{"learn":[4.677426793],"iteration":221,"passed_time":0.3214624073,"remaining_time":1.126566454},
{"learn":[4.673376891],"iteration":222,"passed_time":0.3228845387,"remaining_time":1.125028191},
{"learn":[4.669963188],"iteration":223,"passed_time":0.3244736891,"remaining_time":1.124069566},
{"learn":[4.667565427],"iteration":224,"passed_time":0.3259818994,"remaining_time":1.122826542},
{"learn":[4.664766409],"iteration":225,"passed_time":0.3269952586,"remaining_time":1.119886417},
{"learn":[4.661501396],"iteration":226,"passed_time":0.3280133624,"remaining_time":1.116979424},
{"learn":[4.660156916],"iteration":227,"passed_time":0.3290517182,"remaining_time":1.114157572},
{"learn":[4.655227002],"iteration":228,"passed_time":0.330152661,"remaining_time":1.111562016},
{"learn":[4.64995639],"iteration":229,"passed_time":0.3311259649,"remaining_time":1.108552143},
{"learn":[4.646196804],"iteration":230,"passed_time":0.3321856885,"remaining_time":1.105847595},
{"learn":[4.640603241],"iteration":231,"passed_time":0.3332579585,"remaining_time":1.103198759},
{"learn":[4.634668858],"iteration":232,"passed_time":0.3344934905,"remaining_time":1.101100889},
{"learn":[4.629467485],"iteration":233,"passed_time":0.3357619376,"remaining_time":1.099118138},
{"learn":[4.624836105],"iteration":234,"passed_time":0.3376894902,"remaining_time":1.099287064},
{"learn":[4.622976873],"iteration":235,"passed_time":0.3393551256,"remaining_time":1.098590322},
{"learn":[4.621448221],"iteration":236,"passed_time":0.340804917,"remaining_time":1.097190513},
{"learn":[4.617279625],"iteration":237,"passed_time":0.3418560157,"remaining_time":1.094513798},
{"learn":[4.614246868],"iteration":238,"passed_time":0.3427963796,"remaining_time":1.091498096},
{"learn":[4.60991674],"iteration":239,"passed_time":0.3438154304,"remaining_time":1.088748863},
{"learn":[4.608237778],"iteration":240,"passed_time":0.3449211471,"remaining_time":1.086286932},
{"learn":[4.603843273],"iteration":241,"passed_time":0.3460469022,"remaining_time":1.083898975},
{"learn":[4.601442353],"iteration":242,"passed_time":0.3470695386,"remaining_time":1.081200168},
{"learn":[4.597029194],"iteration":243,"passed_time":0.3480256628,"remaining_time":1.078309021},
{"learn":[4.594358918],"iteration":244,"passed_time":0.3489856276,"remaining_time":1.075445505},
{"learn":[4.593365362],"iteration":245,"passed_time":0.3500397752,"remaining_time":1.07288614},
{"learn":[4.58568171],"iteration":246,"passed_time":0.3516050609,"remaining_time":1.07189721},
{"learn":[4.584934985],"iteration":247,"passed_time":0.35287601,"remaining_time":1.070011127},
{"learn":[4.578428011],"iteration":248,"passed_time":0.3547559249,"remaining_time":1.069966665},
{"learn":[4.574164308],"iteration":249,"passed_time":0.3559518672,"remaining_time":1.067855602},
{"learn":[4.569012913],"iteration":250,"passed_time":0.3569345481,"remaining_time":1.065115444},
{"learn":[4.564743488],"iteration":251,"passed_time":0.3582271752,"remaining_time":1.063309234},
{"learn":[4.563303393],"iteration":252,"passed_time":0.3595154897,"remaining_time":1.061494351},
{"learn":[4.561506545],"iteration":253,"passed_time":0.3606402916,"remaining_time":1.059203376},
{"learn":[4.558375689],"iteration":254,"passed_time":0.3617686288,"remaining_time":1.056931876},
{"learn":[4.554520058],"iteration":255,"passed_time":0.3635040512,"remaining_time":1.056433649},
{"learn":[4.550103269],"iteration":256,"passed_time":0.3655440289,"remaining_time":1.056806278},
{"learn":[4.546389306],"iteration":257,"passed_time":0.3683447501,"remaining_time":1.05934808},
{"learn":[4.538564891],"iteration":258,"passed_time":0.3694446915,"remaining_time":1.056982689},
{"learn":[4.537038153],"iteration":259,"passed_time":0.3704736964,"remaining_time":1.054425136},
{"learn":[4.532471001],"iteration":260,"passed_time":0.3717338891,"remaining_time":1.052533885},
{"learn":[4.529830341],"iteration":261,"passed_time":0.3728372031,"remaining_time":1.050205557},
{"learn":[4.525416495],"iteration":262,"passed_time":0.374083161,"remaining_time":1.048286272},
{"learn":[4.523673868],"iteration":263,"passed_time":0.3751589009,"remaining_time":1.045897542},
{"learn":[4.523317892],"iteration":264,"passed_time":0.376206139,"remaining_time":1.043439669},
{"learn":[4.52266057],"iteration":265,"passed_time":0.3773918006,"remaining_time":1.041374367},
{"learn":[4.519947879],"iteration":266,"passed_time":0.3792759238,"remaining_time":1.041233154},
{"learn":[4.517499575],"iteration":267,"passed_time":0.3810798896,"remaining_time":1.040859997},
{"learn":[4.515060456],"iteration":268,"passed_time":0.3820398296,"remaining_time":1.038182585},
{"learn":[4.510604695],"iteration":269,"passed_time":0.3829594731,"remaining_time":1.035408946},
{"learn":[4.50500471],"iteration":270,"passed_time":0.3840170405,"remaining_time":1.033020009},
{"learn":[4.499471403],"iteration":271,"passed_time":0.3850403886,"remaining_time":1.030549275},
{"learn":[4.497583597],"iteration":272,"passed_time":0.3859647963,"remaining_time":1.027825666},
{"learn":[4.495796492],"iteration":273,"passed_time":0.3869230915,"remaining_time":1.02520498},
{"learn":[4.49305114],"iteration":274,"passed_time":0.3878554776,"remaining_time":1.022528077},
{"learn":[4.486424276],"iteration":275,"passed_time":0.3889778624,"remaining_time":1.020362219},
{"learn":[4.480523955],"iteration":276,"passed_time":0.389872027,"remaining_time":1.017608215},
{"learn":[4.478071796],"iteration":277,"passed_time":0.3910948178,"remaining_time":1.015721074},
{"learn":[4.474454071],"iteration":278,"passed_time":0.3924994749,"remaining_time":1.014308679},
{"learn":[4.469991748],"iteration":279,"passed_time":0.3942331771,"remaining_time":1.013742455},
{"learn":[4.46668793],"iteration":280,"passed_time":0.3958284491,"remaining_time":1.012813718},
{"learn":[4.460651401],"iteration":281,"passed_time":0.3970443681,"remaining_time":1.010914384},
{"learn":[4.455332199],"iteration":282,"passed_time":0.3982520954,"remaining_time":1.008999125},
{"learn":[4.452452378],"iteration":283,"passed_time":0.39932101,"remaining_time":1.006738884},
{"learn":[4.44984297],"iteration":284,"passed_time":0.4002728976,"remaining_time":1.00419341},
{"learn":[4.445451837],"iteration":285,"passed_time":0.4011884645,"remaining_time":1.001568404},
{"learn":[4.437831605],"iteration":286,"passed_time":0.4022911968,"remaining_time":0.9994202904},
{"learn":[4.433682],"iteration":287,"passed_time":0.4035629034,"remaining_time":0.9976971778},
{"learn":[4.429043306],"iteration":288,"passed_time":0.4053198284,"remaining_time":0.9971709273},
{"learn":[4.427869553],"iteration":289,"passed_time":0.4097394404,"remaining_time":1.003155182},
{"learn":[4.426773136],"iteration":290,"passed_time":0.4116873819,"remaining_time":1.003045889},
{"learn":[4.422741686],"iteration":291,"passed_time":0.412884628,"remaining_time":1.001103824},
{"learn":[4.420200017],"iteration":292,"passed_time":0.4138471917,"remaining_time":0.9986005616},
{"learn":[4.418733532],"iteration":293,"passed_time":0.4148532503,"remaining_time":0.9962122268},
{"learn":[4.417217169],"iteration":294,"passed_time":0.4159491275,"remaining_time":0.9940479149},
{"learn":[4.41206261],"iteration":295,"passed_time":0.4169186514,"remaining_time":0.991590306},
{"learn":[4.405798264],"iteration":296,"passed_time":0.4180130544,"remaining_time":0.9894383072},
{"learn":[4.399204642],"iteration":297,"passed_time":0.4195823312,"remaining_time":0.9884120688},
{"learn":[4.39304093],"iteration":298,"passed_time":0.4214937013,"remaining_time":0.9881842295},
{"learn":[4.388209736],"iteration":299,"passed_time":0.4226130679,"remaining_time":0.9860971585},
{"learn":[4.382438836],"iteration":300,"passed_time":0.4235285045,"remaining_time":0.9835429389},
{"learn":[4.380540804],"iteration":301,"passed_time":0.4242604754,"remaining_time":0.9805755358},
{"learn":[4.3769442],"iteration":302,"passed_time":0.425072267,"remaining_time":0.9778065021},
{"learn":[4.373378139],"iteration":303,"passed_time":0.4258406991,"remaining_time":0.9749510742},
{"learn":[4.368660712],"iteration":304,"passed_time":0.4266119182,"remaining_time":0.9721156825},
{"learn":[4.364703475],"iteration":305,"passed_time":0.4273725673,"remaining_time":0.9692698094},
{"learn":[4.361843265],"iteration":306,"passed_time":0.4281216629,"remaining_time":0.9664114411},
{"learn":[4.358008396],"iteration":307,"passed_time":0.4289722023,"remaining_time":0.9637946884},
{"learn":[4.353608965],"iteration":308,"passed_time":0.4298930842,"remaining_time":0.9613466704},
{"learn":[4.348586285],"iteration":309,"passed_time":0.4307285247,"remaining_time":0.9587183291},
{"learn":[4.346649499],"iteration":310,"passed_time":0.431871319,"remaining_time":0.9567824398},
{"learn":[4.34437877],"iteration":311,"passed_time":0.4334440401,"remaining_time":0.9557996781},
{"learn":[4.337925185],"iteration":312,"passed_time":0.4352099955,"remaining_time":0.9552372744},
{"learn":[4.331965899],"iteration":313,"passed_time":0.4371470355,"remaining_time":0.9550409757},
{"learn":[4.328877006],"iteration":314,"passed_time":0.4382385974,"remaining_time":0.9529950452},
{"learn":[4.326382416],"iteration":315,"passed_time":0.439384815,"remaining_time":0.9510734603},
{"learn":[4.326145222],"iteration":316,"passed_time":0.4403205603,"remaining_time":0.9487032891},
{"learn":[4.325370011],"iteration":317,"passed_time":0.4410840533,"remaining_time":0.945972718},
{"learn":[4.323004035],"iteration":318,"passed_time":0.4419858704,"remaining_time":0.9435497736},
{"learn":[4.31916786],"iteration":319,"passed_time":0.442801593,"remaining_time":0.9409533851},
{"learn":[4.313362385],"iteration":320,"passed_time":0.4437221544,"remaining_time":0.938589853},
{"learn":[4.307815846],"iteration":321,"passed_time":0.4445713895,"remaining_time":0.9360850997},
{"learn":[4.303555424],"iteration":322,"passed_time":0.4455007764,"remaining_time":0.9337585933},
{"learn":[4.299648928],"iteration":323,"passed_time":0.4467491254,"remaining_time":0.9321061999},
{"learn":[4.29694752],"iteration":324,"passed_time":0.4481528637,"remaining_time":0.9307790245},
{"learn":[4.293878916],"iteration":325,"passed_time":0.4500075155,"remaining_time":0.9303836364},
{"learn":[4.289902999],"iteration":326,"passed_time":0.4510506011,"remaining_time":0.9283090353},
{"learn":[4.287749846],"iteration":327,"passed_time":0.4522887907,"remaining_time":0.9266404493},
{"learn":[4.285523591],"iteration":328,"passed_time":0.4535330642,"remaining_time":0.9249868877},
{"learn":[4.283914361],"iteration":329,"passed_time":0.4544848997,"remaining_time":0.9227420692},
{"learn":[4.279657343],"iteration":330,"passed_time":0.4560144169,"remaining_time":0.9216726431},
{"learn":[4.276545471],"iteration":331,"passed_time":0.4570765026,"remaining_time":0.919659951},
{"learn":[4.273267166],"iteration":332,"passed_time":0.4580045552,"remaining_time":0.9173844994},
{"learn":[4.26738637],"iteration":333,"passed_time":0.4589686777,"remaining_time":0.91518904},
{"learn":[4.263174904],"iteration":334,"passed_time":0.4604735493,"remaining_time":0.914074359},
{"learn":[4.259782871],"iteration":335,"passed_time":0.4621666278,"remaining_time":0.9133292883},
{"learn":[4.256918345],"iteration":336,"passed_time":0.463359697,"remaining_time":0.9115948935},
{"learn":[4.252682329],"iteration":337,"passed_time":0.4643441689,"remaining_time":0.9094551473},
{"learn":[4.247848362],"iteration":338,"passed_time":0.4652735748,"remaining_time":0.9072148465},
{"learn":[4.243659487],"iteration":339,"passed_time":0.4661221982,"remaining_time":0.9048254436},
{"learn":[4.23941961],"iteration":340,"passed_time":0.4669628486,"remaining_time":0.9024296693},
{"learn":[4.234389944],"iteration":341,"passed_time":0.4677901704,"remaining_time":0.9000173454},
{"learn":[4.231705968],"iteration":342,"passed_time":0.4686460758,"remaining_time":0.897669014},
{"learn":[4.226502343],"iteration":343,"passed_time":0.4694968354,"remaining_time":0.8953195465},
{"learn":[4.221096684],"iteration":344,"passed_time":0.4704378148,"remaining_time":0.8931500542},
{"learn":[4.218345975],"iteration":345,"passed_time":0.471301923,"remaining_time":0.8908423631},
{"learn":[4.216873754],"iteration":346,"passed_time":0.4721227059,"remaining_time":0.8884614609},
{"learn":[4.21352793],"iteration":347,"passed_time":0.472930762,"remaining_time":0.8860656805},
{"learn":[4.207198015],"iteration":348,"passed_time":0.4737902367,"remaining_time":0.8837749115},
{"learn":[4.201613779],"iteration":349,"passed_time":0.4751226598,"remaining_time":0.8823706539},
{"learn":[4.195735371],"iteration":350,"passed_time":0.4760755436,"remaining_time":0.8802650365},
{"learn":[4.195570955],"iteration":351,"passed_time":0.4767499433,"remaining_time":0.8776533048},
{"learn":[4.19358764],"iteration":352,"passed_time":0.4777474973,"remaining_time":0.8756448463},
{"learn":[4.190109607],"iteration":353,"passed_time":0.4786401589,"remaining_time":0.8734506855},
{"learn":[4.188480001],"iteration":354,"passed_time":0.4795222181,"remaining_time":0.8712445934},
{"learn":[4.186621745],"iteration":355,"passed_time":0.4803489782,"remaining_time":0.8689459045},
{"learn":[4.18278109],"iteration":356,"passed_time":0.481182539,"remaining_time":0.8666677104},
{"learn":[4.176893873],"iteration":357,"passed_time":0.4821186052,"remaining_time":0.8645814094},
{"learn":[4.17202968],"iteration":358,"passed_time":0.4831248242,"remaining_time":0.8626267753},
{"learn":[4.169196393],"iteration":359,"passed_time":0.4839091527,"remaining_time":0.8602829381},
{"learn":[4.167006558],"iteration":360,"passed_time":0.4846965782,"remaining_time":0.8579532229},
{"learn":[4.160403857],"iteration":361,"passed_time":0.485556074,"remaining_time":0.8557590475},
{"learn":[4.159920462],"iteration":362,"passed_time":0.4863545624,"remaining_time":0.8534651688},
{"learn":[4.155991553],"iteration":363,"passed_time":0.4872695978,"remaining_time":0.8513831435},
{"learn":[4.153005954],"iteration":364,"passed_time":0.4887652418,"remaining_time":0.8503176124},
{"learn":[4.14966273],"iteration":365,"passed_time":0.4898659038,"remaining_time":0.8485655274},
{"learn":[4.14486578],"iteration":366,"passed_time":0.4910281434,"remaining_time":0.846923201},
{"learn":[4.141890013],"iteration":367,"passed_time":0.4918350209,"remaining_time":0.844673188},
{"learn":[4.13779053],"iteration":368,"passed_time":0.4926085472,"remaining_time":0.8423739655},
{"learn":[4.135190163],"iteration":369,"passed_time":0.4933900871,"remaining_time":0.8400966348},
{"learn":[4.13487713],"iteration":370,"passed_time":0.4941284312,"remaining_time":0.8377541327},
{"learn":[4.13389459],"iteration":371,"passed_time":0.4949391851,"remaining_time":0.8355424953},
{"learn":[4.131874331],"iteration":372,"passed_time":0.4957539707,"remaining_time":0.8333451464},
{"learn":[4.131722018],"iteration":373,"passed_time":0.4963106902,"remaining_time":0.8307232407},
{"learn":[4.12926704],"iteration":374,"passed_time":0.4972602754,"remaining_time":0.8287671257},
{"learn":[4.126565177],"iteration":375,"passed_time":0.4982693026,"remaining_time":0.8269150128},
{"learn":[4.121715689],"iteration":376,"passed_time":0.4991081477,"remaining_time":0.8247861433},
{"learn":[4.116928082],"iteration":377,"passed_time":0.5000394654,"remaining_time":0.8228162631},
{"learn":[4.114115064],"iteration":378,"passed_time":0.5008654681,"remaining_time":0.8206793027},
{"learn":[4.111894932],"iteration":379,"passed_time":0.5016880162,"remaining_time":0.8185436053},
{"learn":[4.111462485],"iteration":380,"passed_time":0.5024198419,"remaining_time":0.8162674071},
{"learn":[4.108940518],"iteration":381,"passed_time":0.5033443547,"remaining_time":0.814311024},
{"learn":[4.104797141],"iteration":382,"passed_time":0.5042350096,"remaining_time":0.8123054854},
{"learn":[4.097740482],"iteration":383,"passed_time":0.5054353598,"remaining_time":0.8108025564},
{"learn":[4.097089102],"iteration":384,"passed_time":0.5062997789,"remaining_time":0.8087645818},
{"learn":[4.091919812],"iteration":385,"passed_time":0.5072675768,"remaining_time":0.8068971299},
{"learn":[4.091740499],"iteration":386,"passed_time":0.5078972973,"remaining_time":0.8044988198},
{"learn":[4.087630877],"iteration":387,"passed_time":0.5087301857,"remaining_time":0.8024300868},
{"learn":[4.08570924],"iteration":388,"passed_time":0.5094364576,"remaining_time":0.8001688318},
{"learn":[4.079828416],"iteration":389,"passed_time":0.5102320171,"remaining_time":0.7980552062},
{"learn":[4.078677284],"iteration":390,"passed_time":0.5111255054,"remaining_time":0.7961008512},
{"learn":[4.078230263],"iteration":391,"passed_time":0.5120847787,"remaining_time":0.7942539425},
{"learn":[4.076433227],"iteration":392,"passed_time":0.5128698135,"remaining_time":0.7921424346},
{"learn":[4.071484309],"iteration":393,"passed_time":0.5137478013,"remaining_time":0.7901806284},
{"learn":[4.068838272],"iteration":394,"passed_time":0.5146827342,"remaining_time":0.7883115296},
{"learn":[4.066304839],"iteration":395,"passed_time":0.5155914867,"remaining_time":0.7864072171},
{"learn":[4.065961136],"iteration":396,"passed_time":0.5164216319,"remaining_time":0.784388524},
{"learn":[4.063848768],"iteration":397,"passed_time":0.5171853498,"remaining_time":0.7822753281},
{"learn":[4.059636621],"iteration":398,"passed_time":0.5183096903,"remaining_time":0.7807120899},
{"learn":[4.057488925],"iteration":399,"passed_time":0.5191831254,"remaining_time":0.7787746882},
{"learn":[4.053193743],"iteration":400,"passed_time":0.5201773393,"remaining_time":0.777023008},
{"learn":[4.051346862],"iteration":401,"passed_time":0.5210930471,"remaining_time":0.7751583138},
{"learn":[4.047316227],"iteration":402,"passed_time":0.5219994021,"remaining_time":0.7732844741},
{"learn":[4.042253647],"iteration":403,"passed_time":0.5228526035,"remaining_time":0.7713370092},
{"learn":[4.038767928],"iteration":404,"passed_time":0.5237888502,"remaining_time":0.7695169528},
{"learn":[4.035169304],"iteration":405,"passed_time":0.5247984896,"remaining_time":0.7678086277},
{"learn":[4.032928402],"iteration":406,"passed_time":0.5257419572,"remaining_time":0.7660073234},
{"learn":[4.029709594],"iteration":407,"passed_time":0.5267752192,"remaining_time":0.7643405141},
{"learn":[4.026929955],"iteration":408,"passed_time":0.5277411364,"remaining_time":0.7625794905},
{"learn":[4.025196906],"iteration":409,"passed_time":0.5286436556,"remaining_time":0.7607311142},
{"learn":[4.020445425],"iteration":410,"passed_time":0.5295277716,"remaining_time":0.7588609671},
{"learn":[4.015943909],"iteration":411,"passed_time":0.5303954902,"remaining_time":0.7569722045},
{"learn":[4.011750717],"iteration":412,"passed_time":0.5312174265,"remaining_time":0.7550233156},
{"learn":[4.008351503],"iteration":413,"passed_time":0.5321198454,"remaining_time":0.7531937908},
{"learn":[4.005422074],"iteration":414,"passed_time":0.5333661938,"remaining_time":0.7518535503},
{"learn":[4.00304587],"iteration":415,"passed_time":0.5344757965,"remaining_time":0.7503217912},
{"learn":[4.002823219],"iteration":416,"passed_time":0.5354760587,"remaining_time":0.74863919},
{"learn":[3.999670059],"iteration":417,"passed_time":0.5364184528,"remaining_time":0.7468792811},
{"learn":[3.99924718],"iteration":418,"passed_time":0.5373149851,"remaining_time":0.7450596811},
{"learn":[3.997675362],"iteration":419,"passed_time":0.5382651569,"remaining_time":0.74331855},
{"learn":[3.992434207],"iteration":420,"passed_time":0.5392887065,"remaining_time":0.7416820927},
{"learn":[3.990594866],"iteration":421,"passed_time":0.5402321588,"remaining_time":0.7399388336},
{"learn":[3.986549965],"iteration":422,"passed_time":0.5410827426,"remaining_time":0.7380726772},
{"learn":[3.983411518],"iteration":423,"passed_time":0.5420897037,"remaining_time":0.7364237485},
{"learn":[3.983000428],"iteration":424,"passed_time":0.5429659871,"remaining_time":0.7346010414},
{"learn":[3.9825614],"iteration":425,"passed_time":0.5438424362,"remaining_time":0.7327830008},
{"learn":[3.979296271],"iteration":426,"passed_time":0.5447078027,"remaining_time":0.7309544987},
{"learn":[3.97572913],"iteration":427,"passed_time":0.5456027701,"remaining_time":0.7291700572},
{"learn":[3.974134237],"iteration":428,"passed_time":0.5464938916,"remaining_time":0.7273846436},
{"learn":[3.97233739],"iteration":429,"passed_time":0.547502422,"remaining_time":0.7257590246},
{"learn":[3.970802487],"iteration":430,"passed_time":0.5485207064,"remaining_time":0.724149146},
{"learn":[3.967899334],"iteration":431,"passed_time":0.549517097,"remaining_time":0.7225132201},
{"learn":[3.967734033],"iteration":432,"passed_time":0.5504350007,"remaining_time":0.720777472},
{"learn":[3.966058024],"iteration":433,"passed_time":0.5513344907,"remaining_time":0.7190214786},
{"learn":[3.965841558],"iteration":434,"passed_time":0.5521437254,"remaining_time":0.7171521951},
{"learn":[3.960918627],"iteration":435,"passed_time":0.5529808408,"remaining_time":0.7153238399},
{"learn":[3.959559161],"iteration":436,"passed_time":0.5539298339,"remaining_time":0.7136441567},
{"learn":[3.955016069],"iteration":437,"passed_time":0.5547884862,"remaining_time":0.7118518933},
{"learn":[3.953378798],"iteration":438,"passed_time":0.5556172527,"remaining_time":0.710025692},
{"learn":[3.95141538],"iteration":439,"passed_time":0.556473543,"remaining_time":0.7082390548},
{"learn":[3.946746691],"iteration":440,"passed_time":0.5573476448,"remaining_time":0.7064792142},
{"learn":[3.941960349],"iteration":441,"passed_time":0.5582129971,"remaining_time":0.7047123357},
{"learn":[3.938973946],"iteration":442,"passed_time":0.5590358808,"remaining_time":0.7028961301},
{"learn":[3.937947251],"iteration":443,"passed_time":0.5599579313,"remaining_time":0.7012085806},
{"learn":[3.93583508],"iteration":444,"passed_time":0.5608659869,"remaining_time":0.6995070174},
{"learn":[3.934567233],"iteration":445,"passed_time":0.5618998554,"remaining_time":0.6979652912},
{"learn":[3.929785107],"iteration":446,"passed_time":0.5629634302,"remaining_time":0.6964625882},
{"learn":[3.9257215],"iteration":447,"passed_time":0.564133182,"remaining_time":0.6950926707},
{"learn":[3.922603796],"iteration":448,"passed_time":0.565178815,"remaining_time":0.6935713297},
{"learn":[3.922341013],"iteration":449,"passed_time":0.566048365,"remaining_time":0.6918368906},
{"learn":[3.917980702],"iteration":450,"passed_time":0.5668806651,"remaining_time":0.6900609426},
{"learn":[3.915049515],"iteration":451,"passed_time":0.5678976351,"remaining_time":0.6885130621},
{"learn":[3.910757125],"iteration":452,"passed_time":0.5688663858,"remaining_time":0.6869093003},
{"learn":[3.909628171],"iteration":453,"passed_time":0.5697685139,"remaining_time":0.6852282128},
{"learn":[3.90686956],"iteration":454,"passed_time":0.5707434926,"remaining_time":0.6836378098},
{"learn":[3.903117863],"iteration":455,"passed_time":0.5715741139,"remaining_time":0.6818778903},
{"learn":[3.900884863],"iteration":456,"passed_time":0.5725392843,"remaining_time":0.6802819067},
{"learn":[3.898410477],"iteration":457,"passed_time":0.5734421707,"remaining_time":0.6786149706},
{"learn":[3.898079368],"iteration":458,"passed_time":0.5743864402,"remaining_time":0.6770001397},
{"learn":[3.897758665],"iteration":459,"passed_time":0.5751410518,"remaining_time":0.6751655825},
{"learn":[3.894055259],"iteration":460,"passed_time":0.5761438251,"remaining_time":0.6736258606},
{"learn":[3.893759305],"iteration":461,"passed_time":0.5773959851,"remaining_time":0.6723788745},
{"learn":[3.8898663],"iteration":462,"passed_time":0.578620415,"remaining_time":0.6710997038},
{"learn":[3.88796479],"iteration":463,"passed_time":0.5796006689,"remaining_time":0.6695387038},
{"learn":[3.885189407],"iteration":464,"passed_time":0.5804386616,"remaining_time":0.6678165246},
{"learn":[3.881999923],"iteration":465,"passed_time":0.5813263441,"remaining_time":0.666155081},
{"learn":[3.880394291],"iteration":466,"passed_time":0.5822060612,"remaining_time":0.66448786},
{"learn":[3.877159649],"iteration":467,"passed_time":0.5830351844,"remaining_time":0.6627664917},
{"learn":[3.87576691],"iteration":468,"passed_time":0.583927177,"remaining_time":0.6611201087},
{"learn":[3.874675212],"iteration":469,"passed_time":0.5848131082,"remaining_time":0.6594701008},
{"learn":[3.873083796],"iteration":470,"passed_time":0.5856266101,"remaining_time":0.6577419888},
{"learn":[3.872281103],"iteration":471,"passed_time":0.5866370011,"remaining_time":0.6562380013},
{"learn":[3.871422244],"iteration":472,"passed_time":0.58747501,"remaining_time":0.6545440387},
{"learn":[3.868616358],"iteration":473,"passed_time":0.5885317489,"remaining_time":0.6530964133},
{"learn":[3.866751895],"iteration":474,"passed_time":0.5894639941,"remaining_time":0.6515128355},
{"learn":[3.863778392],"iteration":475,"passed_time":0.5902338397,"remaining_time":0.6497532185},
{"learn":[3.859313423],"iteration":476,"passed_time":0.59104481,"remaining_time":0.6480428419},
{"learn":[3.856600816],"iteration":477,"passed_time":0.592223893,"remaining_time":0.6467382262},
{"learn":[3.854779643],"iteration":478,"passed_time":0.5933547084,"remaining_time":0.6453816348},
{"learn":[3.851686796],"iteration":479,"passed_time":0.5944095174,"remaining_time":0.6439436439},
{"learn":[3.849877908],"iteration":480,"passed_time":0.5958644231,"remaining_time":0.6429389513},
{"learn":[3.845717663],"iteration":481,"passed_time":0.5969763234,"remaining_time":0.6415637666},
{"learn":[3.841199743],"iteration":482,"passed_time":0.5978250169,"remaining_time":0.6399079374},
{"learn":[3.836251997],"iteration":483,"passed_time":0.5987654161,"remaining_time":0.6383532123},
{"learn":[3.833994331],"iteration":484,"passed_time":0.5996265696,"remaining_time":0.6367168728},
{"learn":[3.831313212],"iteration":485,"passed_time":0.600599328,"remaining_time":0.6352017585},
{"learn":[3.826940968],"iteration":486,"passed_time":0.6014901472,"remaining_time":0.6336025575},
{"learn":[3.825594688],"iteration":487,"passed_time":0.6023919902,"remaining_time":0.6320178258},
{"learn":[3.821533908],"iteration":488,"passed_time":0.6033851008,"remaining_time":0.6305312608},
{"learn":[3.818079741],"iteration":489,"passed_time":0.6043121853,"remaining_time":0.6289779888},
{"learn":[3.815974508],"iteration":490,"passed_time":0.6056186973,"remaining_time":0.6278206047},
{"learn":[3.814127515],"iteration":491,"passed_time":0.6068918389,"remaining_time":0.6266281589},
{"learn":[3.810085842],"iteration":492,"passed_time":0.6081072321,"remaining_time":0.6253759974},
{"learn":[3.807675051],"iteration":493,"passed_time":0.6091153614,"remaining_time":0.623911686},
{"learn":[3.80729979],"iteration":494,"passed_time":0.6100538852,"remaining_time":0.6223782061},
{"learn":[3.803468883],"iteration":495,"passed_time":0.6112175489,"remaining_time":0.6210758965},
{"learn":[3.800887346],"iteration":496,"passed_time":0.6123252317,"remaining_time":0.6197174881},
{"learn":[3.798034917],"iteration":497,"passed_time":0.6132418116,"remaining_time":0.6181674486},
{"learn":[3.797848605],"iteration":498,"passed_time":0.6139882496,"remaining_time":0.6164491243},
{"learn":[3.795827057],"iteration":499,"passed_time":0.6149728761,"remaining_time":0.6149728761},
{"learn":[3.795645928],"iteration":500,"passed_time":0.6158109189,"remaining_time":0.6133525919},
{"learn":[3.794239891],"iteration":501,"passed_time":0.6166829997,"remaining_time":0.6117691909},
{"learn":[3.794053573],"iteration":502,"passed_time":0.6174439897,"remaining_time":0.6100788527},
{"learn":[3.793481372],"iteration":503,"passed_time":0.6181893498,"remaining_time":0.6083768205},
{"learn":[3.793292219],"iteration":504,"passed_time":0.6189852408,"remaining_time":0.6067281073},
{"learn":[3.7895243],"iteration":505,"passed_time":0.6205813007,"remaining_time":0.6058639576},
{"learn":[3.787967533],"iteration":506,"passed_time":0.6220795527,"remaining_time":0.6049018136},
{"learn":[3.785449807],"iteration":507,"passed_time":0.6233190256,"remaining_time":0.6036869303},
{"learn":[3.783379523],"iteration":508,"passed_time":0.6243391791,"remaining_time":0.6022603869},
{"learn":[3.77852881],"iteration":509,"passed_time":0.6253852634,"remaining_time":0.6008603511},
{"learn":[3.778168072],"iteration":510,"passed_time":0.6262779403,"remaining_time":0.5993148979},
{"learn":[3.775124432],"iteration":511,"passed_time":0.6272148528,"remaining_time":0.5978141566},
{"learn":[3.774841],"iteration":512,"passed_time":0.628255136,"remaining_time":0.5964137451},
{"learn":[3.772367928],"iteration":513,"passed_time":0.6291980864,"remaining_time":0.5949227042},
{"learn":[3.768441674],"iteration":514,"passed_time":0.629999413,"remaining_time":0.5933004181},
{"learn":[3.766985866],"iteration":515,"passed_time":0.6308724231,"remaining_time":0.5917485519},
{"learn":[3.766084298],"iteration":516,"passed_time":0.6318612614,"remaining_time":0.5903075227},
{"learn":[3.76392991],"iteration":517,"passed_time":0.6328284676,"remaining_time":0.5888481108},
{"learn":[3.760342404],"iteration":518,"passed_time":0.6341162649,"remaining_time":0.5876877138},
{"learn":[3.758376547],"iteration":519,"passed_time":0.6352334849,"remaining_time":0.5863693706},
{"learn":[3.754882254],"iteration":520,"passed_time":0.6362405563,"remaining_time":0.5849505307},
{"learn":[3.754794699],"iteration":521,"passed_time":0.6373023417,"remaining_time":0.5835833704},
{"learn":[3.751914445],"iteration":522,"passed_time":0.6383864564,"remaining_time":0.5822377432},
{"learn":[3.751655602],"iteration":523,"passed_time":0.6394214123,"remaining_time":0.5808484585},
{"learn":[3.750932725],"iteration":524,"passed_time":0.6403612494,"remaining_time":0.5793744637},
{"learn":[3.749129643],"iteration":525,"passed_time":0.6412374687,"remaining_time":0.5778451714},
{"learn":[3.747658066],"iteration":526,"passed_time":0.6420752245,"remaining_time":0.5762838353},
{"learn":[3.745099213],"iteration":527,"passed_time":0.6429945122,"remaining_time":0.5747981245},
{"learn":[3.744931581],"iteration":528,"passed_time":0.6437227275,"remaining_time":0.5731444322},
{"learn":[3.743975602],"iteration":529,"passed_time":0.6445545623,"remaining_time":0.5715861213},
{"learn":[3.739603588],"iteration":530,"passed_time":0.645444104,"remaining_time":0.5700815156},
{"learn":[3.738817674],"iteration":531,"passed_time":0.6464064424,"remaining_time":0.5686432613},
{"learn":[3.735079],"iteration":532,"passed_time":0.647389077,"remaining_time":0.5672245759},
{"learn":[3.733302315],"iteration":533,"passed_time":0.6482912251,"remaining_time":0.5657372864},
{"learn":[3.731874415],"iteration":534,"passed_time":0.6493667545,"remaining_time":0.5644028801},
{"learn":[3.72849124],"iteration":535,"passed_time":0.6503348987,"remaining_time":0.5629764795},
{"learn":[3.725068548],"iteration":536,"passed_time":0.6512810388,"remaining_time":0.5615328137},
{"learn":[3.723286665],"iteration":537,"passed_time":0.6520368691,"remaining_time":0.5599275716},
{"learn":[3.720918762],"iteration":538,"passed_time":0.652816057,"remaining_time":0.5583454588},
{"learn":[3.717996078],"iteration":539,"passed_time":0.6538401472,"remaining_time":0.5569749402},
{"learn":[3.716416422],"iteration":540,"passed_time":0.6547965723,"remaining_time":0.5555482933},
{"learn":[3.711982645],"iteration":541,"passed_time":0.6557169884,"remaining_time":0.5540929533},
{"learn":[3.711735657],"iteration":542,"passed_time":0.6566378407,"remaining_time":0.5526399506},
{"learn":[3.709823131],"iteration":543,"passed_time":0.6576044198,"remaining_time":0.5512272343},
{"learn":[3.707233897],"iteration":544,"passed_time":0.6585631468,"remaining_time":0.5498095996},
{"learn":[3.703340065],"iteration":545,"passed_time":0.6595205045,"remaining_time":0.5483925074},
{"learn":[3.699157537],"iteration":546,"passed_time":0.6604933871,"remaining_time":0.5469899532},
{"learn":[3.695988943],"iteration":547,"passed_time":0.6614461865,"remaining_time":0.545572402},
{"learn":[3.694321381],"iteration":548,"passed_time":0.6623027929,"remaining_time":0.5440775221},
{"learn":[3.694140708],"iteration":549,"passed_time":0.6637196037,"remaining_time":0.5430433122},
{"learn":[3.693803806],"iteration":550,"passed_time":0.6648633613,"remaining_time":0.5417852073},
{"learn":[3.691870278],"iteration":551,"passed_time":0.6658832097,"remaining_time":0.5404269528},
{"learn":[3.689783447],"iteration":552,"passed_time":0.6668177105,"remaining_time":0.5390009341},
{"learn":[3.687386728],"iteration":553,"passed_time":0.6677609082,"remaining_time":0.5375836915},
{"learn":[3.685161836],"iteration":554,"passed_time":0.6686984186,"remaining_time":0.5361635969},
{"learn":[3.684869972],"iteration":555,"passed_time":0.6695182578,"remaining_time":0.5346512706},
{"learn":[3.68358714],"iteration":556,"passed_time":0.6704395823,"remaining_time":0.5332221454},
{"learn":[3.682060777],"iteration":557,"passed_time":0.6714067384,"remaining_time":0.531831144},
{"learn":[3.680952499],"iteration":558,"passed_time":0.6722686101,"remaining_time":0.5303585994},
{"learn":[3.678509334],"iteration":559,"passed_time":0.6731423752,"remaining_time":0.5288975805},
{"learn":[3.674865272],"iteration":560,"passed_time":0.6739696679,"remaining_time":0.5274022891},
{"learn":[3.674157972],"iteration":561,"passed_time":0.6749190426,"remaining_time":0.5260045207},
{"learn":[3.673640839],"iteration":562,"passed_time":0.6758387615,"remaining_time":0.5245853264},
{"learn":[3.672566305],"iteration":563,"passed_time":0.6771971076,"remaining_time":0.5235069839},
{"learn":[3.669620915],"iteration":564,"passed_time":0.6785020812,"remaining_time":0.5223865581},
{"learn":[3.665634934],"iteration":565,"passed_time":0.6804823462,"remaining_time":0.5217832832},
{"learn":[3.663582569],"iteration":566,"passed_time":0.6815553784,"remaining_time":0.520482326},
{"learn":[3.66050246],"iteration":567,"passed_time":0.6824804127,"remaining_time":0.5190696097},
{"learn":[3.658697512],"iteration":568,"passed_time":0.6833664743,"remaining_time":0.5176290869},
{"learn":[3.6577754],"iteration":569,"passed_time":0.6842011374,"remaining_time":0.5161517352},
{"learn":[3.655981485],"iteration":570,"passed_time":0.6850876102,"remaining_time":0.51471556},
{"learn":[3.653818997],"iteration":571,"passed_time":0.6859487899,"remaining_time":0.5132623812},
{"learn":[3.651734664],"iteration":572,"passed_time":0.6868553407,"remaining_time":0.5118450794},
{"learn":[3.647821227],"iteration":573,"passed_time":0.6877630951,"remaining_time":0.5104304503},
{"learn":[3.64648951],"iteration":574,"passed_time":0.6887784896,"remaining_time":0.5090971445},
{"learn":[3.64516238],"iteration":575,"passed_time":0.6897763855,"remaining_time":0.5077520616},
{"learn":[3.641245284],"iteration":576,"passed_time":0.6906849923,"remaining_time":0.506342724},
{"learn":[3.640114077],"iteration":577,"passed_time":0.6918787282,"remaining_time":0.5051432929},
{"learn":[3.63907372],"iteration":578,"passed_time":0.6929196371,"remaining_time":0.5038327585},
{"learn":[3.637914774],"iteration":579,"passed_time":0.6937548522,"remaining_time":0.5023742033},
{"learn":[3.636109081],"iteration":580,"passed_time":0.6945737195,"remaining_time":0.5009060043},
{"learn":[3.634201205],"iteration":581,"passed_time":0.6954176895,"remaining_time":0.4994580656},
{"learn":[3.631841843],"iteration":582,"passed_time":0.6962584496,"remaining_time":0.4980099031},
{"learn":[3.631104551],"iteration":583,"passed_time":0.6971752105,"remaining_time":0.4966179582},
{"learn":[3.629394881],"iteration":584,"passed_time":0.6979422681,"remaining_time":0.495121438},
{"learn":[3.629079853],"iteration":585,"passed_time":0.698711532,"remaining_time":0.4936289663},
{"learn":[3.624573951],"iteration":586,"passed_time":0.6995729419,"remaining_time":0.4922037905},
{"learn":[3.623343285],"iteration":587,"passed_time":0.7003776789,"remaining_time":0.4907408226},
{"learn":[3.622265205],"iteration":588,"passed_time":0.7011302341,"remaining_time":0.4892436778},
{"learn":[3.619117809],"iteration":589,"passed_time":0.7019094922,"remaining_time":0.4877676132},
{"learn":[3.615486244],"iteration":590,"passed_time":0.7027535672,"remaining_time":0.4863387631},
{"learn":[3.611856127],"iteration":591,"passed_time":0.7035947395,"remaining_time":0.4849098881},
{"learn":[3.609766399],"iteration":592,"passed_time":0.7044526393,"remaining_time":0.4834944759},
{"learn":[3.606439317],"iteration":593,"passed_time":0.7053511072,"remaining_time":0.4821086693},
{"learn":[3.602696766],"iteration":594,"passed_time":0.7070219615,"remaining_time":0.4812502427},
{"learn":[3.599339415],"iteration":595,"passed_time":0.7081337959,"remaining_time":0.4800101569},
{"learn":[3.596082533],"iteration":596,"passed_time":0.7090129275,"remaining_time":0.4786134167},
{"learn":[3.592912037],"iteration":597,"passed_time":0.7099229942,"remaining_time":0.4772392035},
{"learn":[3.592721255],"iteration":598,"passed_time":0.7108184334,"remaining_time":0.4758567476},
{"learn":[3.589239305],"iteration":599,"passed_time":0.7116641685,"remaining_time":0.474442779},
{"learn":[3.585991785],"iteration":600,"passed_time":0.7125284672,"remaining_time":0.4730430256},
{"learn":[3.582776444],"iteration":601,"passed_time":0.7133682851,"remaining_time":0.4716288662},
{"learn":[3.579679235],"iteration":602,"passed_time":0.714198341,"remaining_time":0.4702101847},
{"learn":[3.577450113],"iteration":603,"passed_time":0.7152794957,"remaining_time":0.46895808},
{"learn":[3.576319286],"iteration":604,"passed_time":0.7160791876,"remaining_time":0.4675227754},
{"learn":[3.575223811],"iteration":605,"passed_time":0.7168951719,"remaining_time":0.4661001613},
{"learn":[3.573472927],"iteration":606,"passed_time":0.717704326,"remaining_time":0.4646751237},
{"learn":[3.570759149],"iteration":607,"passed_time":0.7185458689,"remaining_time":0.4632729944},
{"learn":[3.566340555],"iteration":608,"passed_time":0.7193315751,"remaining_time":0.4618368569},
{"learn":[3.563833624],"iteration":609,"passed_time":0.7205801204,"remaining_time":0.4606987655},
{"learn":[3.561919181],"iteration":610,"passed_time":0.7215757789,"remaining_time":0.4593993093},
{"learn":[3.558371979],"iteration":611,"passed_time":0.7228554876,"remaining_time":0.4582809301},
{"learn":[3.557802595],"iteration":612,"passed_time":0.7236846758,"remaining_time":0.4568776012},
{"learn":[3.557198589],"iteration":613,"passed_time":0.7244698047,"remaining_time":0.455448444},
{"learn":[3.556572197],"iteration":614,"passed_time":0.7254388471,"remaining_time":0.4541365141},
{"learn":[3.555851069],"iteration":615,"passed_time":0.726185947,"remaining_time":0.4526873436},
{"learn":[3.554134779],"iteration":616,"passed_time":0.726946556,"remaining_time":0.4512488346},
{"learn":[3.552083242],"iteration":617,"passed_time":0.7277824124,"remaining_time":0.4498590316},
{"learn":[3.55018277],"iteration":618,"passed_time":0.7290026402,"remaining_time":0.4487076024},
{"learn":[3.547923483],"iteration":619,"passed_time":0.729698171,"remaining_time":0.4472343628},
{"learn":[3.545198235],"iteration":620,"passed_time":0.730516928,"remaining_time":0.4458388337},
{"learn":[3.544208067],"iteration":621,"passed_time":0.731305588,"remaining_time":0.4444268686},
{"learn":[3.54251234],"iteration":622,"passed_time":0.7321729155,"remaining_time":0.4430645091},
{"learn":[3.540408827],"iteration":623,"passed_time":0.7331767175,"remaining_time":0.4417859708},
{"learn":[3.537393081],"iteration":624,"passed_time":0.7339780943,"remaining_time":0.4403868566},
{"learn":[3.533396636],"iteration":625,"passed_time":0.7350016024,"remaining_time":0.4391223631},
{"learn":[3.533305239],"iteration":626,"passed_time":0.7360410283,"remaining_time":0.4378681078},
{"learn":[3.529753263],"iteration":627,"passed_time":0.7374611539,"remaining_time":0.4368400466},
{"learn":[3.528340533],"iteration":628,"passed_time":0.7382904815,"remaining_time":0.4354622713},
{"learn":[3.526188096],"iteration":629,"passed_time":0.7391514396,"remaining_time":0.4341048138},
{"learn":[3.52464681],"iteration":630,"passed_time":0.7400129212,"remaining_time":0.432749236},
{"learn":[3.52302112],"iteration":631,"passed_time":0.7409854518,"remaining_time":0.4314598833},
{"learn":[3.522862594],"iteration":632,"passed_time":0.7419703702,"remaining_time":0.4301787138},
{"learn":[3.521205285],"iteration":633,"passed_time":0.7429568412,"remaining_time":0.4288993752},
{"learn":[3.519085964],"iteration":634,"passed_time":0.7437929785,"remaining_time":0.4275345467},
{"learn":[3.516081076],"iteration":635,"passed_time":0.7444978061,"remaining_time":0.4260962287},
{"learn":[3.513291263],"iteration":636,"passed_time":0.7453696667,"remaining_time":0.4247553988},
{"learn":[3.511680826],"iteration":637,"passed_time":0.7461072491,"remaining_time":0.4233398498},
{"learn":[3.509215823],"iteration":638,"passed_time":0.7468490341,"remaining_time":0.421928797},
{"learn":[3.507962493],"iteration":639,"passed_time":0.7475928292,"remaining_time":0.4205209664},
{"learn":[3.506836126],"iteration":640,"passed_time":0.7482931739,"remaining_time":0.4190908727},
{"learn":[3.505394121],"iteration":641,"passed_time":0.7496305149,"remaining_time":0.4180182622},
{"learn":[3.502700117],"iteration":642,"passed_time":0.7510789381,"remaining_time":0.4170065022},
{"learn":[3.499743017],"iteration":643,"passed_time":0.7523063709,"remaining_time":0.4158712237},
{"learn":[3.498187188],"iteration":644,"passed_time":0.7533168479,"remaining_time":0.4146162496},
{"learn":[3.494300758],"iteration":645,"passed_time":0.754303701,"remaining_time":0.4133490869},
{"learn":[3.492663227],"iteration":646,"passed_time":0.755061496,"remaining_time":0.4119578178},
{"learn":[3.488299425],"iteration":647,"passed_time":0.7559878742,"remaining_time":0.4106600798},
{"learn":[3.486629103],"iteration":648,"passed_time":0.7569673058,"remaining_time":0.4093921792},
{"learn":[3.485196842],"iteration":649,"passed_time":0.7579260576,"remaining_time":0.408114031},
{"learn":[3.482481486],"iteration":650,"passed_time":0.7589716905,"remaining_time":0.4068834408},
{"learn":[3.480862059],"iteration":651,"passed_time":0.7598108824,"remaining_time":0.4055432317},
{"learn":[3.479640012],"iteration":652,"passed_time":0.7605917542,"remaining_time":0.4041735661},
{"learn":[3.475721877],"iteration":653,"passed_time":0.7614197942,"remaining_time":0.4028306557},
{"learn":[3.474480662],"iteration":654,"passed_time":0.7621937255,"remaining_time":0.4014608173},
{"learn":[3.473832277],"iteration":655,"passed_time":0.7633570544,"remaining_time":0.400296992},
{"learn":[3.470567213],"iteration":656,"passed_time":0.7648481696,"remaining_time":0.3993042955},
{"learn":[3.467221536],"iteration":657,"passed_time":0.7660171295,"remaining_time":0.3981426418},
{"learn":[3.464619684],"iteration":658,"passed_time":0.7670313512,"remaining_time":0.3969008965},
{"learn":[3.463888288],"iteration":659,"passed_time":0.7678893417,"remaining_time":0.3955793578},
{"learn":[3.462127113],"iteration":660,"passed_time":0.7687217382,"remaining_time":0.3942460957},
{"learn":[3.459478331],"iteration":661,"passed_time":0.7704438315,"remaining_time":0.3933686028},
{"learn":[3.457990358],"iteration":662,"passed_time":0.7718406947,"remaining_time":0.392323249},
{"learn":[3.455005757],"iteration":663,"passed_time":0.7726423623,"remaining_time":0.3909756532},
{"learn":[3.450842971],"iteration":664,"passed_time":0.7734751409,"remaining_time":0.3896453717},
{"learn":[3.450736399],"iteration":665,"passed_time":0.7742458581,"remaining_time":0.3882854603},
{"learn":[3.449424086],"iteration":666,"passed_time":0.7750765095,"remaining_time":0.3869572379},
{"learn":[3.446915499],"iteration":667,"passed_time":0.7759710366,"remaining_time":0.3856622517},
{"learn":[3.444896543],"iteration":668,"passed_time":0.7770373985,"remaining_time":0.3844534812},
{"learn":[3.441560213],"iteration":669,"passed_time":0.7783346288,"remaining_time":0.383358847},
{"learn":[3.440693164],"iteration":670,"passed_time":0.7797457794,"remaining_time":0.3823194656},
{"learn":[3.438854758],"iteration":671,"passed_time":0.7809406739,"remaining_time":0.3811734242},
{"learn":[3.438755891],"iteration":672,"passed_time":0.7818629994,"remaining_time":0.3798948006},
{"learn":[3.438514224],"iteration":673,"passed_time":0.7827250215,"remaining_time":0.3785880668},
{"learn":[3.437869325],"iteration":674,"passed_time":0.7837647875,"remaining_time":0.377368231},
{"learn":[3.436202325],"iteration":675,"passed_time":0.7847911147,"remaining_time":0.3761424869},
{"learn":[3.43469564],"iteration":676,"passed_time":0.7856029718,"remaining_time":0.3748150072},
{"learn":[3.434561647],"iteration":677,"passed_time":0.7865543823,"remaining_time":0.3735553261},
{"learn":[3.43176184],"iteration":678,"passed_time":0.7875748024,"remaining_time":0.3723291776},
{"learn":[3.429924052],"iteration":679,"passed_time":0.7885436624,"remaining_time":0.3710793706},
{"learn":[3.428852642],"iteration":680,"passed_time":0.7894797186,"remaining_time":0.3698150224},
{"learn":[3.425703708],"iteration":681,"passed_time":0.7905140498,"remaining_time":0.3685974602},
{"learn":[3.421961552],"iteration":682,"passed_time":0.7920070261,"remaining_time":0.3675933049},
{"learn":[3.421813474],"iteration":683,"passed_time":0.7933967137,"remaining_time":0.3665400022},
{"learn":[3.421063236],"iteration":684,"passed_time":0.7943862445,"remaining_time":0.3653017037},
{"learn":[3.419854895],"iteration":685,"passed_time":0.7953202251,"remaining_time":0.3640387036},
{"learn":[3.418744811],"iteration":686,"passed_time":0.7965132881,"remaining_time":0.3628947004},
{"learn":[3.417883689],"iteration":687,"passed_time":0.7975058576,"remaining_time":0.3616596331},
{"learn":[3.416194741],"iteration":688,"passed_time":0.7985358315,"remaining_time":0.3604421533},
{"learn":[3.412895307],"iteration":689,"passed_time":0.7995394028,"remaining_time":0.3592133549},
{"learn":[3.412317631],"iteration":690,"passed_time":0.8006055389,"remaining_time":0.358013186},
{"learn":[3.408457025],"iteration":691,"passed_time":0.8015824833,"remaining_time":0.3567737064},
{"learn":[3.406729312],"iteration":692,"passed_time":0.8025284079,"remaining_time":0.3555212428},
{"learn":[3.40515438],"iteration":693,"passed_time":0.8037026226,"remaining_time":0.3543703206},
{"learn":[3.402120642],"iteration":694,"passed_time":0.8047406135,"remaining_time":0.3531595498},
{"learn":[3.399685031],"iteration":695,"passed_time":0.806273475,"remaining_time":0.3521654259},
{"learn":[3.398505478],"iteration":696,"passed_time":0.8079270112,"remaining_time":0.3512222158},
{"learn":[3.397764036],"iteration":697,"passed_time":0.8094086045,"remaining_time":0.3502025767},
{"learn":[3.397681148],"iteration":698,"passed_time":0.8105804624,"remaining_time":0.3490482392},
{"learn":[3.395314306],"iteration":699,"passed_time":0.8116231325,"remaining_time":0.3478384853},
{"learn":[3.392588443],"iteration":700,"passed_time":0.8126793002,"remaining_time":0.3466349654},
{"learn":[3.389449247],"iteration":701,"passed_time":0.8138183833,"remaining_time":0.345467063},
{"learn":[3.388125803],"iteration":702,"passed_time":0.8149560122,"remaining_time":0.3442986282},
{"learn":[3.387764251],"iteration":703,"passed_time":0.8159829072,"remaining_time":0.3430837223},
{"learn":[3.386199649],"iteration":704,"passed_time":0.8171681375,"remaining_time":0.3419356036},
{"learn":[3.384914045],"iteration":705,"passed_time":0.8182507975,"remaining_time":0.3407446664},
{"learn":[3.38128396],"iteration":706,"passed_time":0.8195484753,"remaining_time":0.3396431446},
{"learn":[3.379787724],"iteration":707,"passed_time":0.8209091629,"remaining_time":0.3385670559},
{"learn":[3.378546921],"iteration":708,"passed_time":0.8220593281,"remaining_time":0.3374037581},
{"learn":[3.375590701],"iteration":709,"passed_time":0.8232556872,"remaining_time":0.3362593652},
{"learn":[3.374300939],"iteration":710,"passed_time":0.8247614805,"remaining_time":0.3352406018},
{"learn":[3.373182293],"iteration":711,"passed_time":0.8261061375,"remaining_time":0.3341552916},
{"learn":[3.371715046],"iteration":712,"passed_time":0.8271627021,"remaining_time":0.3329532896},
{"learn":[3.368963454],"iteration":713,"passed_time":0.8282234138,"remaining_time":0.3317533562},
{"learn":[3.367647694],"iteration":714,"passed_time":0.8293041129,"remaining_time":0.3305617793},
{"learn":[3.366695211],"iteration":715,"passed_time":0.8304923735,"remaining_time":0.3294131761},
{"learn":[3.364319775],"iteration":716,"passed_time":0.8315153208,"remaining_time":0.3281992131},
{"learn":[3.361140747],"iteration":717,"passed_time":0.8325966919,"remaining_time":0.3270087286},
{"learn":[3.358199674],"iteration":718,"passed_time":0.8339289033,"remaining_time":0.3259165811},
{"learn":[3.356038283],"iteration":719,"passed_time":0.8354747629,"remaining_time":0.3249068522},
{"learn":[3.355952617],"iteration":720,"passed_time":0.8371851128,"remaining_time":0.3239592878},
{"learn":[3.35586871],"iteration":721,"passed_time":0.8381338858,"remaining_time":0.3227163715},
{"learn":[3.353568685],"iteration":722,"passed_time":0.8390768619,"remaining_time":0.3214720481},
{"learn":[3.350571416],"iteration":723,"passed_time":0.8400563627,"remaining_time":0.3202424808},
{"learn":[3.348181669],"iteration":724,"passed_time":0.8409657317,"remaining_time":0.3189870017},
{"learn":[3.347249279],"iteration":725,"passed_time":0.8419122481,"remaining_time":0.3177464959},
{"learn":[3.346437519],"iteration":726,"passed_time":0.843659425,"remaining_time":0.3168074595},
{"learn":[3.345057784],"iteration":727,"passed_time":0.8445062828,"remaining_time":0.3155298199},
{"learn":[3.341766025],"iteration":728,"passed_time":0.8453256215,"remaining_time":0.3142431323},
{"learn":[3.340738293],"iteration":729,"passed_time":0.8463619481,"remaining_time":0.3130379808},
{"learn":[3.338375944],"iteration":730,"passed_time":0.8477727462,"remaining_time":0.3119710927},
{"learn":[3.33568642],"iteration":731,"passed_time":0.8494282323,"remaining_time":0.3109928501},
{"learn":[3.331103862],"iteration":732,"passed_time":0.8517787477,"remaining_time":0.3102659286},
{"learn":[3.327228096],"iteration":733,"passed_time":0.8529714157,"remaining_time":0.3091149817},
{"learn":[3.325045112],"iteration":734,"passed_time":0.8542140745,"remaining_time":0.3079819452},
{"learn":[3.322600677],"iteration":735,"passed_time":0.8552736673,"remaining_time":0.3067829459},
{"learn":[3.321514509],"iteration":736,"passed_time":0.8567436413,"remaining_time":0.3057307702},
{"learn":[3.318793776],"iteration":737,"passed_time":0.8583245718,"remaining_time":0.3047168534},
{"learn":[3.316383036],"iteration":738,"passed_time":0.8597035786,"remaining_time":0.3036300866},
{"learn":[3.3140738],"iteration":739,"passed_time":0.86127477,"remaining_time":0.3026100543},
{"learn":[3.312052332],"iteration":740,"passed_time":0.8628616386,"remaining_time":0.301594014},
{"learn":[3.30796958],"iteration":741,"passed_time":0.8640653376,"remaining_time":0.3004432036},
{"learn":[3.305912335],"iteration":742,"passed_time":0.8650431937,"remaining_time":0.2992141329},
{"learn":[3.304542143],"iteration":743,"passed_time":0.8661648975,"remaining_time":0.2980352335},
{"learn":[3.301567614],"iteration":744,"passed_time":0.8670429861,"remaining_time":0.2967731026},
{"learn":[3.300142459],"iteration":745,"passed_time":0.8678073358,"remaining_time":0.2954732752},
{"learn":[3.300026633],"iteration":746,"passed_time":0.8685773519,"remaining_time":0.2941768006},
{"learn":[3.297451468],"iteration":747,"passed_time":0.8694228463,"remaining_time":0.2929071621},
{"learn":[3.296311137],"iteration":748,"passed_time":0.8703381324,"remaining_time":0.2916620444},
{"learn":[3.293860413],"iteration":749,"passed_time":0.8711304831,"remaining_time":0.2903768277},
{"learn":[3.290223581],"iteration":750,"passed_time":0.8719063562,"remaining_time":0.2890874603},
{"learn":[3.287722815],"iteration":751,"passed_time":0.8727499851,"remaining_time":0.2878218036},
{"learn":[3.287649366],"iteration":752,"passed_time":0.8737862601,"remaining_time":0.2866204598},
{"learn":[3.286119593],"iteration":753,"passed_time":0.8751506546,"remaining_time":0.2855266061},
{"learn":[3.281746331],"iteration":754,"passed_time":0.8765196825,"remaining_time":0.2844335393},
{"learn":[3.278659379],"iteration":755,"passed_time":0.8776868969,"remaining_time":0.2832746069},
{"learn":[3.277453351],"iteration":756,"passed_time":0.8785775327,"remaining_time":0.2820268698},
{"learn":[3.276325594],"iteration":757,"passed_time":0.879567936,"remaining_time":0.2808119268},
{"learn":[3.276154158],"iteration":758,"passed_time":0.8803929311,"remaining_time":0.2795450545},
{"learn":[3.272479607],"iteration":759,"passed_time":0.881310202,"remaining_time":0.2783084848},
{"learn":[3.271500582],"iteration":760,"passed_time":0.8821989925,"remaining_time":0.2770638097},
{"learn":[3.270483287],"iteration":761,"passed_time":0.8831243477,"remaining_time":0.2758314892},
{"learn":[3.26977168],"iteration":762,"passed_time":0.8840565427,"remaining_time":0.2746020978},
{"learn":[3.267109281],"iteration":763,"passed_time":0.884978458,"remaining_time":0.273370309},
{"learn":[3.264265386],"iteration":764,"passed_time":0.8858271516,"remaining_time":0.2721168374},
{"learn":[3.264126246],"iteration":765,"passed_time":0.8866463599,"remaining_time":0.2708554154},
{"learn":[3.262218612],"iteration":766,"passed_time":0.8878851403,"remaining_time":0.2697226046},
{"learn":[3.260995018],"iteration":767,"passed_time":0.8890086594,"remaining_time":0.2685546992},
{"learn":[3.25993043],"iteration":768,"passed_time":0.8901658449,"remaining_time":0.2673970223},
{"learn":[3.258530092],"iteration":769,"passed_time":0.8912188591,"remaining_time":0.2662082307},
{"learn":[3.258028289],"iteration":770,"passed_time":0.8923746601,"remaining_time":0.2650503206},
{"learn":[3.257109549],"iteration":771,"passed_time":0.8932979541,"remaining_time":0.2638237481},
{"learn":[3.255387117],"iteration":772,"passed_time":0.894097606,"remaining_time":0.2625616514},
{"learn":[3.254756436],"iteration":773,"passed_time":0.8949144174,"remaining_time":0.2613057601},
{"learn":[3.253920124],"iteration":774,"passed_time":0.8956749662,"remaining_time":0.2600346676},
{"learn":[3.250896693],"iteration":775,"passed_time":0.8965491434,"remaining_time":0.2587976909},
{"learn":[3.247879406],"iteration":776,"passed_time":0.8975086073,"remaining_time":0.2575861254},
{"learn":[3.245088293],"iteration":777,"passed_time":0.8984825081,"remaining_time":0.2563793275},
{"learn":[3.244590557],"iteration":778,"passed_time":0.8995722337,"remaining_time":0.2552059867},
{"learn":[3.242732343],"iteration":779,"passed_time":0.9003682646,"remaining_time":0.2539500233},
{"learn":[3.241741152],"iteration":780,"passed_time":0.9011599286,"remaining_time":0.2526940133},
{"learn":[3.239755495],"iteration":781,"passed_time":0.902331721,"remaining_time":0.2515451601},
{"learn":[3.236849227],"iteration":782,"passed_time":0.9036192538,"remaining_time":0.2504283245},
{"learn":[3.235990219],"iteration":783,"passed_time":0.9047748695,"remaining_time":0.2492747089},
{"learn":[3.234695396],"iteration":784,"passed_time":0.9057588843,"remaining_time":0.2480740893},
{"learn":[3.233132994],"iteration":785,"passed_time":0.9066818072,"remaining_time":0.2468573877},
{"learn":[3.232137381],"iteration":786,"passed_time":0.9075309025,"remaining_time":0.2456214514},
{"learn":[3.231318298],"iteration":787,"passed_time":0.9085632365,"remaining_time":0.2444357946},
{"learn":[3.231208774],"iteration":788,"passed_time":0.9093375154,"remaining_time":0.2431815155},
{"learn":[3.228466522],"iteration":789,"passed_time":0.9102674539,"remaining_time":0.2419698295},
{"learn":[3.226894845],"iteration":790,"passed_time":0.9111719087,"remaining_time":0.2407521225},
{"learn":[3.224832254],"iteration":791,"passed_time":0.912038995,"remaining_time":0.2395253926},
{"learn":[3.222729715],"iteration":792,"passed_time":0.9128922819,"remaining_time":0.2382959676},
{"learn":[3.219740635],"iteration":793,"passed_time":0.9137893959,"remaining_time":0.2370788609},
{"learn":[3.219164632],"iteration":794,"passed_time":0.9146504748,"remaining_time":0.2358532671},
{"learn":[3.2180235],"iteration":795,"passed_time":0.9154536072,"remaining_time":0.2346137385},
{"learn":[3.216300435],"iteration":796,"passed_time":0.9165253557,"remaining_time":0.233443723},
{"learn":[3.215629732],"iteration":797,"passed_time":0.9181380427,"remaining_time":0.232410883},
{"learn":[3.213516063],"iteration":798,"passed_time":0.9195195715,"remaining_time":0.2313184404},
{"learn":[3.211240036],"iteration":799,"passed_time":0.9206732621,"remaining_time":0.2301683155},
{"learn":[3.210390944],"iteration":800,"passed_time":0.9217839278,"remaining_time":0.2290074927},
{"learn":[3.207822584],"iteration":801,"passed_time":0.9227566758,"remaining_time":0.2278127454},
{"learn":[3.206783402],"iteration":802,"passed_time":0.9238318184,"remaining_time":0.2266436715},
{"learn":[3.20509165],"iteration":803,"passed_time":0.9248979807,"remaining_time":0.2254726421},
{"learn":[3.20421922],"iteration":804,"passed_time":0.9259169924,"remaining_time":0.2242904516},
{"learn":[3.204150522],"iteration":805,"passed_time":0.9269728993,"remaining_time":0.2231175465},
{"learn":[3.204049473],"iteration":806,"passed_time":0.9279738894,"remaining_time":0.2219317976},
{"learn":[3.199751986],"iteration":807,"passed_time":0.9288678137,"remaining_time":0.2207210647},
{"learn":[3.199284757],"iteration":808,"passed_time":0.9298294295,"remaining_time":0.2195270965},
{"learn":[3.199030807],"iteration":809,"passed_time":0.9314586988,"remaining_time":0.2184903121},
{"learn":[3.198341691],"iteration":810,"passed_time":0.9328003686,"remaining_time":0.2173850427},
{"learn":[3.197868305],"iteration":811,"passed_time":0.9345597354,"remaining_time":0.2163758993},
{"learn":[3.19576385],"iteration":812,"passed_time":0.9358170804,"remaining_time":0.2152494392},
{"learn":[3.194039874],"iteration":813,"passed_time":0.9368986172,"remaining_time":0.214082485},
{"learn":[3.192925592],"iteration":814,"passed_time":0.9378879674,"remaining_time":0.2128948147},
{"learn":[3.192206381],"iteration":815,"passed_time":0.9388682309,"remaining_time":0.2117055815},
{"learn":[3.189745658],"iteration":816,"passed_time":0.9409971299,"remaining_time":0.2107741429},
{"learn":[3.185742291],"iteration":817,"passed_time":0.941975082,"remaining_time":0.2095836979},
{"learn":[3.1852757],"iteration":818,"passed_time":0.9427878417,"remaining_time":0.2083572642},
{"learn":[3.183192206],"iteration":819,"passed_time":0.9437530321,"remaining_time":0.2071652997},
{"learn":[3.182490086],"iteration":820,"passed_time":0.9446891484,"remaining_time":0.2059675488},
{"learn":[3.17988999],"iteration":821,"passed_time":0.9457586905,"remaining_time":0.2047993271},
{"learn":[3.177080671],"iteration":822,"passed_time":0.9471699605,"remaining_time":0.2037048396},
{"learn":[3.176033114],"iteration":823,"passed_time":0.9484379162,"remaining_time":0.2025789724},
{"learn":[3.172533363],"iteration":824,"passed_time":0.9493898588,"remaining_time":0.2013857276},
{"learn":[3.171305324],"iteration":825,"passed_time":0.9503606448,"remaining_time":0.2001970366},
{"learn":[3.169420057],"iteration":826,"passed_time":0.9513963543,"remaining_time":0.1990224538},
{"learn":[3.167800585],"iteration":827,"passed_time":0.952447859,"remaining_time":0.1978514876},
{"learn":[3.167298508],"iteration":828,"passed_time":0.9535434817,"remaining_time":0.19668991},
{"learn":[3.166855962],"iteration":829,"passed_time":0.9545653412,"remaining_time":0.1955133831},
{"learn":[3.165728671],"iteration":830,"passed_time":0.955598638,"remaining_time":0.1943395545},
{"learn":[3.164529228],"iteration":831,"passed_time":0.9569285629,"remaining_time":0.1932259598},
{"learn":[3.161432456],"iteration":832,"passed_time":0.9582889759,"remaining_time":0.1921179579},
{"learn":[3.160410726],"iteration":833,"passed_time":0.9595043997,"remaining_time":0.190980492},
{"learn":[3.159683969],"iteration":834,"passed_time":0.9606959249,"remaining_time":0.1898381169},
{"learn":[3.157620751],"iteration":835,"passed_time":0.9618297127,"remaining_time":0.1886842977},
{"learn":[3.155118717],"iteration":836,"passed_time":0.9630547491,"remaining_time":0.1875482964},
{"learn":[3.15457858],"iteration":837,"passed_time":0.9644645396,"remaining_time":0.1864477988},
{"learn":[3.154528318],"iteration":838,"passed_time":0.9655051332,"remaining_time":0.1852757169},
{"learn":[3.153542148],"iteration":839,"passed_time":0.9665946377,"remaining_time":0.1841132643},
{"learn":[3.152373359],"iteration":840,"passed_time":0.9676107353,"remaining_time":0.1829371069},
{"learn":[3.150427457],"iteration":841,"passed_time":0.9688746192,"remaining_time":0.1818078264},
{"learn":[3.147006319],"iteration":842,"passed_time":0.9699258484,"remaining_time":0.1806386218},
{"learn":[3.146417542],"iteration":843,"passed_time":0.9709675098,"remaining_time":0.1794679284},
{"learn":[3.146359599],"iteration":844,"passed_time":0.9724417318,"remaining_time":0.1783768857},
{"learn":[3.144546404],"iteration":845,"passed_time":0.973978455,"remaining_time":0.1772963145},
{"learn":[3.142524235],"iteration":846,"passed_time":0.9760412281,"remaining_time":0.1763096906},
{"learn":[3.140945123],"iteration":847,"passed_time":0.9776756337,"remaining_time":0.1752437457},
{"learn":[3.139733785],"iteration":848,"passed_time":0.9790338202,"remaining_time":0.1741273343},
{"learn":[3.137668278],"iteration":849,"passed_time":0.9802574072,"remaining_time":0.1729866013},
{"learn":[3.136483717],"iteration":850,"passed_time":0.9815007818,"remaining_time":0.1718491381},
{"learn":[3.13478323],"iteration":851,"passed_time":0.9825700029,"remaining_time":0.1706811742},
{"learn":[3.132621835],"iteration":852,"passed_time":0.9836397356,"remaining_time":0.16951353},
{"learn":[3.131627279],"iteration":853,"passed_time":0.9846520823,"remaining_time":0.1683363045},
{"learn":[3.130982244],"iteration":854,"passed_time":0.9860970058,"remaining_time":0.1672328255},
{"learn":[3.130911741],"iteration":855,"passed_time":0.9874253456,"remaining_time":0.1661089366},
{"learn":[3.129824804],"iteration":856,"passed_time":0.9886402379,"remaining_time":0.1649656406},
{"learn":[3.12750187],"iteration":857,"passed_time":0.9898132882,"remaining_time":0.1638152528},
{"learn":[3.126724856],"iteration":858,"passed_time":0.990759936,"remaining_time":0.1626276496},
{"learn":[3.124301517],"iteration":859,"passed_time":0.9917795437,"remaining_time":0.1614524839},
{"learn":[3.122697191],"iteration":860,"passed_time":0.9928497376,"remaining_time":0.1602858461},
{"learn":[3.121882499],"iteration":861,"passed_time":0.993753681,"remaining_time":0.1590928167},
{"learn":[3.120776704],"iteration":862,"passed_time":0.9945713047,"remaining_time":0.1578867541},
{"learn":[3.118854716],"iteration":863,"passed_time":0.9954812554,"remaining_time":0.1566961235},
{"learn":[3.117904327],"iteration":864,"passed_time":0.9962751196,"remaining_time":0.1554880244},
{"learn":[3.117508236],"iteration":865,"passed_time":0.9970049596,"remaining_time":0.1542709753},
{"learn":[3.11678826],"iteration":866,"passed_time":0.9978913631,"remaining_time":0.1530790672},
{"learn":[3.113322822],"iteration":867,"passed_time":0.9988149423,"remaining_time":0.1518935166},
{"learn":[3.112439997],"iteration":868,"passed_time":1.000283173,"remaining_time":0.1507906739},
{"learn":[3.111147686],"iteration":869,"passed_time":1.001838208,"remaining_time":0.1496999621},
{"learn":[3.110709945],"iteration":870,"passed_time":1.003175414,"remaining_time":0.1485759224},
{"learn":[3.108583156],"iteration":871,"passed_time":1.00437961,"remaining_time":0.1474318694},
{"learn":[3.108509574],"iteration":872,"passed_time":1.00535323,"remaining_time":0.1462541354},
{"learn":[3.106012271],"iteration":873,"passed_time":1.006274027,"remaining_time":0.1450692533},
{"learn":[3.103263084],"iteration":874,"passed_time":1.007254787,"remaining_time":0.143893541},
{"learn":[3.100705875],"iteration":875,"passed_time":1.008201093,"remaining_time":0.1427133967},
{"learn":[3.099574698],"iteration":876,"passed_time":1.009186793,"remaining_time":0.1415393107},
{"learn":[3.097333616],"iteration":877,"passed_time":1.010178369,"remaining_time":0.1403664705},
{"learn":[3.095268552],"iteration":878,"passed_time":1.011033597,"remaining_time":0.1391752733},
{"learn":[3.093553267],"iteration":879,"passed_time":1.012014478,"remaining_time":0.1380019743},
{"learn":[3.09116947],"iteration":880,"passed_time":1.012950053,"remaining_time":0.1368229924},
{"learn":[3.088485932],"iteration":881,"passed_time":1.014043734,"remaining_time":0.135665715},
{"learn":[3.086538434],"iteration":882,"passed_time":1.015259389,"remaining_time":0.1345247435},
{"learn":[3.086495023],"iteration":883,"passed_time":1.016335204,"remaining_time":0.133365253},
{"learn":[3.086444156],"iteration":884,"passed_time":1.017441608,"remaining_time":0.1322099264},
{"learn":[3.084994889],"iteration":885,"passed_time":1.018609585,"remaining_time":0.1310626328},
{"learn":[3.084026278],"iteration":886,"passed_time":1.019742014,"remaining_time":0.1299107639},
{"learn":[3.083946997],"iteration":887,"passed_time":1.020661171,"remaining_time":0.1287320396},
{"learn":[3.082170186],"iteration":888,"passed_time":1.021557773,"remaining_time":0.1275510831},
{"learn":[3.080134021],"iteration":889,"passed_time":1.022505442,"remaining_time":0.1263770771},
{"learn":[3.078584621],"iteration":890,"passed_time":1.023386701,"remaining_time":0.125195455},
{"learn":[3.077700107],"iteration":891,"passed_time":1.024267307,"remaining_time":0.1240144273},
{"learn":[3.076599895],"iteration":892,"passed_time":1.02528188,"remaining_time":0.1228501245},
{"learn":[3.0747142],"iteration":893,"passed_time":1.026239619,"remaining_time":0.1216794179},
{"learn":[3.072691372],"iteration":894,"passed_time":1.027339884,"remaining_time":0.1205259082},
{"learn":[3.072035695],"iteration":895,"passed_time":1.028497982,"remaining_time":0.11937923},
{"learn":[3.070942741],"iteration":896,"passed_time":1.029745789,"remaining_time":0.1182428275},
{"learn":[3.067604908],"iteration":897,"passed_time":1.031168974,"remaining_time":0.1171260973},
{"learn":[3.065625416],"iteration":898,"passed_time":1.032810048,"remaining_time":0.1160331645},
{"learn":[3.062022029],"iteration":899,"passed_time":1.033797258,"remaining_time":0.1148663619},
{"learn":[3.060087295],"iteration":900,"passed_time":1.034979561,"remaining_time":0.1137213946},
{"learn":[3.059998605],"iteration":901,"passed_time":1.03601385,"remaining_time":0.1125602631},
{"learn":[3.056581369],"iteration":902,"passed_time":1.037196544,"remaining_time":0.1114153542},
{"learn":[3.055609768],"iteration":903,"passed_time":1.038114518,"remaining_time":0.1102422497},
{"learn":[3.054867605],"iteration":904,"passed_time":1.03903531,"remaining_time":0.109070005},
{"learn":[3.053755795],"iteration":905,"passed_time":1.039939144,"remaining_time":0.1078965558},
{"learn":[3.052750888],"iteration":906,"passed_time":1.040867924,"remaining_time":0.106726259},
{"learn":[3.05210445],"iteration":907,"passed_time":1.041732453,"remaining_time":0.1055499842},
{"learn":[3.05182579],"iteration":908,"passed_time":1.042876977,"remaining_time":0.1044024256},
{"learn":[3.049703688],"iteration":909,"passed_time":1.044155328,"remaining_time":0.1032681093},
{"learn":[3.049019364],"iteration":910,"passed_time":1.045460566,"remaining_time":0.1021361036},
{"learn":[3.048772591],"iteration":911,"passed_time":1.046372167,"remaining_time":0.1009657354},
{"learn":[3.048682393],"iteration":912,"passed_time":1.047180453,"remaining_time":0.09978608921},
{"learn":[3.047139818],"iteration":913,"passed_time":1.048029142,"remaining_time":0.09861105711},
{"learn":[3.046130495],"iteration":914,"passed_time":1.048816408,"remaining_time":0.09743103242},
{"learn":[3.045736653],"iteration":915,"passed_time":1.049767116,"remaining_time":0.09626685346},
{"learn":[3.04397729],"iteration":916,"passed_time":1.050606944,"remaining_time":0.09509310397},
{"learn":[3.043664178],"iteration":917,"passed_time":1.051414494,"remaining_time":0.09391719878},
{"learn":[3.043248992],"iteration":918,"passed_time":1.052318933,"remaining_time":0.09275063503},
{"learn":[3.041381225],"iteration":919,"passed_time":1.053242995,"remaining_time":0.09158634737},
{"learn":[3.041033992],"iteration":920,"passed_time":1.054024003,"remaining_time":0.09041031076},
{"learn":[3.03973548],"iteration":921,"passed_time":1.054901786,"remaining_time":0.08924331808},
{"learn":[3.037126568],"iteration":922,"passed_time":1.055737923,"remaining_time":0.08807347786},
{"learn":[3.03630781],"iteration":923,"passed_time":1.056509448,"remaining_time":0.08689904552},
{"learn":[3.03542815],"iteration":924,"passed_time":1.057679617,"remaining_time":0.08575780681},
{"learn":[3.034242595],"iteration":925,"passed_time":1.059074054,"remaining_time":0.08463442767},
{"learn":[3.031848212],"iteration":926,"passed_time":1.060500759,"remaining_time":0.08351300475},
{"learn":[3.030593854],"iteration":927,"passed_time":1.061504972,"remaining_time":0.0823581444},
{"learn":[3.02972452],"iteration":928,"passed_time":1.062405395,"remaining_time":0.08119567607},
{"learn":[3.027478055],"iteration":929,"passed_time":1.063318866,"remaining_time":0.08003475337},
{"learn":[3.025862845],"iteration":930,"passed_time":1.064139559,"remaining_time":0.0788674861},
{"learn":[3.023472971],"iteration":931,"passed_time":1.065026754,"remaining_time":0.07770581465},
{"learn":[3.021260476],"iteration":932,"passed_time":1.06601511,"remaining_time":0.07655199612},
{"learn":[3.02026256],"iteration":933,"passed_time":1.066896579,"remaining_time":0.07539097878},
{"learn":[3.017685571],"iteration":934,"passed_time":1.067836326,"remaining_time":0.07423461092},
{"learn":[3.015561708],"iteration":935,"passed_time":1.068777908,"remaining_time":0.07307883135},
{"learn":[3.015517259],"iteration":936,"passed_time":1.069562236,"remaining_time":0.07191293582},
{"learn":[3.013071203],"iteration":937,"passed_time":1.07050146,"remaining_time":0.07075809226},
{"learn":[3.009839928],"iteration":938,"passed_time":1.071734305,"remaining_time":0.0696227823},
{"learn":[3.008124183],"iteration":939,"passed_time":1.073386692,"remaining_time":0.06851404415},
{"learn":[3.006812693],"iteration":940,"passed_time":1.074792487,"remaining_time":0.06738868939},
{"learn":[3.005254533],"iteration":941,"passed_time":1.075690232,"remaining_time":0.06623145803},
{"learn":[3.003758105],"iteration":942,"passed_time":1.076527483,"remaining_time":0.06507112037},
{"learn":[3.003363139],"iteration":943,"passed_time":1.077340654,"remaining_time":0.06391003877},
{"learn":[3.001843188],"iteration":944,"passed_time":1.078219172,"remaining_time":0.06275349681},
{"learn":[3.000048787],"iteration":945,"passed_time":1.079021111,"remaining_time":0.06159317123},
{"learn":[2.997841773],"iteration":946,"passed_time":1.079964971,"remaining_time":0.06044154534},
{"learn":[2.996204255],"iteration":947,"passed_time":1.08073981,"remaining_time":0.05928108661},
{"learn":[2.993701018],"iteration":948,"passed_time":1.081722731,"remaining_time":0.05813262308},
{"learn":[2.993319181],"iteration":949,"passed_time":1.082510278,"remaining_time":0.05697422517},
{"learn":[2.993165615],"iteration":950,"passed_time":1.083354499,"remaining_time":0.05581952728},
{"learn":[2.992049566],"iteration":951,"passed_time":1.084124135,"remaining_time":0.05466172108},
{"learn":[2.991998433],"iteration":952,"passed_time":1.084906877,"remaining_time":0.05350537588},
{"learn":[2.989682076],"iteration":953,"passed_time":1.086364907,"remaining_time":0.05238237498},
{"learn":[2.986942143],"iteration":954,"passed_time":1.0877044,"remaining_time":0.0512530869},
{"learn":[2.98487173],"iteration":955,"passed_time":1.088606397,"remaining_time":0.05010322331},
{"learn":[2.983556235],"iteration":956,"passed_time":1.089605792,"remaining_time":0.048958254},
{"learn":[2.98142842],"iteration":957,"passed_time":1.090601395,"remaining_time":0.04781342233},
{"learn":[2.97981317],"iteration":958,"passed_time":1.091539413,"remaining_time":0.04666643997},
{"learn":[2.978981451],"iteration":959,"passed_time":1.092313651,"remaining_time":0.04551306879},
{"learn":[2.978250585],"iteration":960,"passed_time":1.093175282,"remaining_time":0.04436403331},
{"learn":[2.977642445],"iteration":961,"passed_time":1.093941301,"remaining_time":0.04321181853},
{"learn":[2.976611017],"iteration":962,"passed_time":1.095014814,"remaining_time":0.04207222028},
{"learn":[2.975948141],"iteration":963,"passed_time":1.095861197,"remaining_time":0.04092427707},
{"learn":[2.975609938],"iteration":964,"passed_time":1.09675306,"remaining_time":0.03977860838},
{"learn":[2.973990252],"iteration":965,"passed_time":1.097553113,"remaining_time":0.03863023378},
{"learn":[2.972854366],"iteration":966,"passed_time":1.098382296,"remaining_time":0.0374835737},
{"learn":[2.971861255],"iteration":967,"passed_time":1.099729745,"remaining_time":0.03635470233},
{"learn":[2.969223392],"iteration":968,"passed_time":1.101365785,"remaining_time":0.03523461232},
{"learn":[2.967553189],"iteration":969,"passed_time":1.103123242,"remaining_time":0.03411721368},
{"learn":[2.964684173],"iteration":970,"passed_time":1.104342356,"remaining_time":0.03298241847},
{"learn":[2.963786945],"iteration":971,"passed_time":1.105231818,"remaining_time":0.0318379536},
{"learn":[2.961292662],"iteration":972,"passed_time":1.106157444,"remaining_time":0.03069501644},
{"learn":[2.961219564],"iteration":973,"passed_time":1.10694838,"remaining_time":0.02954893007},
{"learn":[2.960343353],"iteration":974,"passed_time":1.107750811,"remaining_time":0.02840386694},
{"learn":[2.95882207],"iteration":975,"passed_time":1.108688682,"remaining_time":0.02726283644},
{"learn":[2.957994032],"iteration":976,"passed_time":1.109519799,"remaining_time":0.02611970867},
{"learn":[2.954628878],"iteration":977,"passed_time":1.110449697,"remaining_time":0.02497944104},
{"learn":[2.953955096],"iteration":978,"passed_time":1.111313875,"remaining_time":0.02383819344},
{"learn":[2.953777158],"iteration":979,"passed_time":1.113100862,"remaining_time":0.02271634411},
{"learn":[2.952094914],"iteration":980,"passed_time":1.114428982,"remaining_time":0.02158425143},
{"learn":[2.951330498],"iteration":981,"passed_time":1.115546924,"remaining_time":0.02044790695},
{"learn":[2.950753428],"iteration":982,"passed_time":1.11648649,"remaining_time":0.01930851508},
{"learn":[2.950066277],"iteration":983,"passed_time":1.117272121,"remaining_time":0.01816702635},
{"learn":[2.947455197],"iteration":984,"passed_time":1.118058595,"remaining_time":0.01702627301},
{"learn":[2.947071116],"iteration":985,"passed_time":1.118807184,"remaining_time":0.01588570038},
{"learn":[2.946566549],"iteration":986,"passed_time":1.1197034,"remaining_time":0.01474786646},
{"learn":[2.944131028],"iteration":987,"passed_time":1.120941245,"remaining_time":0.01361467099},
{"learn":[2.943047922],"iteration":988,"passed_time":1.121869123,"remaining_time":0.01247781633},
{"learn":[2.942364354],"iteration":989,"passed_time":1.122714938,"remaining_time":0.01134055493},
{"learn":[2.942313721],"iteration":990,"passed_time":1.123536634,"remaining_time":0.01020366267},
{"learn":[2.940677074],"iteration":991,"passed_time":1.124359607,"remaining_time":0.009067416186},
{"learn":[2.938726824],"iteration":992,"passed_time":1.12526356,"remaining_time":0.007932371524},
{"learn":[2.938676354],"iteration":993,"passed_time":1.126032032,"remaining_time":0.006796974037},
{"learn":[2.935587119],"iteration":994,"passed_time":1.127268342,"remaining_time":0.005664665035},
{"learn":[2.934393259],"iteration":995,"passed_time":1.128610392,"remaining_time":0.004532571855},
{"learn":[2.931924791],"iteration":996,"passed_time":1.130150123,"remaining_time":0.003400652327},
{"learn":[2.931596767],"iteration":997,"passed_time":1.130981086,"remaining_time":0.002266495162},
{"learn":[2.930275845],"iteration":998,"passed_time":1.131870222,"remaining_time":0.001133003225},
{"learn":[2.930181152],"iteration":999,"passed_time":1.133023787,"remaining_time":0}
]}